{
	"elements": [
		{
			"weight": 1.0,
			"key": {
				"Type": "block",
				"Name": "securitycraft:blocks/alarm"
			}
		},
		{
			"weight": 1.0,
			"key": {
				"Type": "block",
				"Name": "securitycraft:blocks/ancient_debris_mine"
			}
		},
		{
			"weight": 1.0,
			"key": {
				"Type": "block",
				"Name": "securitycraft:blocks/blast_furnace_mine"
			}
		},
		{
			"weight": 1.0,
			"key": {
				"Type": "block",
				"Name": "securitycraft:blocks/block_change_detector"
			}
		},
		{
			"weight": 1.0,
			"key": {
				"Type": "block",
				"Name": "securitycraft:blocks/block_pocket_manager"
			}
		},
		{
			"weight": 1.0,
			"key": {
				"Type": "block",
				"Name": "securitycraft:blocks/block_pocket_wall"
			}
		},
		{
			"weight": 1.0,
			"key": {
				"Type": "block",
				"Name": "securitycraft:blocks/bouncing_betty"
			}
		},
		{
			"weight": 1.0,
			"key": {
				"Type": "block",
				"Name": "securitycraft:blocks/cage_trap"
			}
		},
		{
			"weight": 1.0,
			"key": {
				"Type": "block",
				"Name": "securitycraft:blocks/chiseled_crystal_quartz"
			}
		},
		{
			"weight": 1.0,
			"key": {
				"Type": "block",
				"Name": "securitycraft:blocks/claymore"
			}
		},
		{
			"weight": 1.0,
			"key": {
				"Type": "block",
				"Name": "securitycraft:blocks/coal_mine"
			}
		},
		{
			"weight": 1.0,
			"key": {
				"Type": "block",
				"Name": "securitycraft:blocks/cobbled_deepslate_mine"
			}
		},
		{
			"weight": 1.0,
			"key": {
				"Type": "block",
				"Name": "securitycraft:blocks/cobblestone_mine"
			}
		},
		{
			"weight": 1.0,
			"key": {
				"Type": "block",
				"Name": "securitycraft:blocks/copper_mine"
			}
		},
		{
			"weight": 1.0,
			"key": {
				"Type": "block",
				"Name": "securitycraft:blocks/crystal_quartz"
			}
		},
		{
			"weight": 1.0,
			"key": {
				"Type": "block",
				"Name": "securitycraft:blocks/crystal_quartz_bricks"
			}
		},
		{
			"weight": 1.0,
			"key": {
				"Type": "block",
				"Name": "securitycraft:blocks/crystal_quartz_pillar"
			}
		},
		{
			"weight": 1.0,
			"key": {
				"Type": "block",
				"Name": "securitycraft:blocks/crystal_quartz_slab"
			}
		},
		{
			"weight": 1.0,
			"key": {
				"Type": "block",
				"Name": "securitycraft:blocks/crystal_quartz_stairs"
			}
		},
		{
			"weight": 1.0,
			"key": {
				"Type": "block",
				"Name": "securitycraft:blocks/deepslate_coal_mine"
			}
		},
		{
			"weight": 1.0,
			"key": {
				"Type": "block",
				"Name": "securitycraft:blocks/deepslate_copper_mine"
			}
		},
		{
			"weight": 1.0,
			"key": {
				"Type": "block",
				"Name": "securitycraft:blocks/deepslate_diamond_mine"
			}
		},
		{
			"weight": 1.0,
			"key": {
				"Type": "block",
				"Name": "securitycraft:blocks/deepslate_emerald_mine"
			}
		},
		{
			"weight": 1.0,
			"key": {
				"Type": "block",
				"Name": "securitycraft:blocks/deepslate_gold_mine"
			}
		},
		{
			"weight": 1.0,
			"key": {
				"Type": "block",
				"Name": "securitycraft:blocks/deepslate_iron_mine"
			}
		},
		{
			"weight": 1.0,
			"key": {
				"Type": "block",
				"Name": "securitycraft:blocks/deepslate_lapis_mine"
			}
		},
		{
			"weight": 1.0,
			"key": {
				"Type": "block",
				"Name": "securitycraft:blocks/deepslate_mine"
			}
		},
		{
			"weight": 1.0,
			"key": {
				"Type": "block",
				"Name": "securitycraft:blocks/deepslate_redstone_mine"
			}
		},
		{
			"weight": 1.0,
			"key": {
				"Type": "block",
				"Name": "securitycraft:blocks/diamond_mine"
			}
		},
		{
			"weight": 1.0,
			"key": {
				"Type": "block",
				"Name": "securitycraft:blocks/dirt_mine"
			}
		},
		{
			"weight": 1.0,
			"key": {
				"Type": "block",
				"Name": "securitycraft:blocks/display_case"
			}
		},
		{
			"weight": 1.0,
			"key": {
				"Type": "block",
				"Name": "securitycraft:blocks/electrified_iron_fence"
			}
		},
		{
			"weight": 1.0,
			"key": {
				"Type": "block",
				"Name": "securitycraft:blocks/emerald_mine"
			}
		},
		{
			"weight": 1.0,
			"key": {
				"Type": "block",
				"Name": "securitycraft:blocks/end_stone_mine"
			}
		},
		{
			"weight": 1.0,
			"key": {
				"Type": "block",
				"Name": "securitycraft:blocks/floor_trap"
			}
		},
		{
			"weight": 1.0,
			"key": {
				"Type": "block",
				"Name": "securitycraft:blocks/furnace_mine"
			}
		},
		{
			"weight": 1.0,
			"key": {
				"Type": "block",
				"Name": "securitycraft:blocks/gilded_blackstone_mine"
			}
		},
		{
			"weight": 1.0,
			"key": {
				"Type": "block",
				"Name": "securitycraft:blocks/glow_display_case"
			}
		},
		{
			"weight": 1.0,
			"key": {
				"Type": "block",
				"Name": "securitycraft:blocks/gold_mine"
			}
		},
		{
			"weight": 1.0,
			"key": {
				"Type": "block",
				"Name": "securitycraft:blocks/gravel_mine"
			}
		},
		{
			"weight": 1.0,
			"key": {
				"Type": "block",
				"Name": "securitycraft:blocks/ims"
			}
		},
		{
			"weight": 1.0,
			"key": {
				"Type": "block",
				"Name": "securitycraft:blocks/inventory_scanner"
			}
		},
		{
			"weight": 1.0,
			"key": {
				"Type": "block",
				"Name": "securitycraft:blocks/iron_door_reinforced"
			}
		},
		{
			"weight": 1.0,
			"key": {
				"Type": "block",
				"Name": "securitycraft:blocks/iron_mine"
			}
		},
		{
			"weight": 1.0,
			"key": {
				"Type": "block",
				"Name": "securitycraft:blocks/key_panel"
			}
		},
		{
			"weight": 1.0,
			"key": {
				"Type": "block",
				"Name": "securitycraft:blocks/keycard_lock"
			}
		},
		{
			"weight": 1.0,
			"key": {
				"Type": "block",
				"Name": "securitycraft:blocks/keycard_reader"
			}
		},
		{
			"weight": 1.0,
			"key": {
				"Type": "block",
				"Name": "securitycraft:blocks/keypad"
			}
		},
		{
			"weight": 1.0,
			"key": {
				"Type": "block",
				"Name": "securitycraft:blocks/keypad_barrel"
			}
		},
		{
			"weight": 1.0,
			"key": {
				"Type": "block",
				"Name": "securitycraft:blocks/keypad_blast_furnace"
			}
		},
		{
			"weight": 1.0,
			"key": {
				"Type": "block",
				"Name": "securitycraft:blocks/keypad_chest"
			}
		},
		{
			"weight": 1.0,
			"key": {
				"Type": "block",
				"Name": "securitycraft:blocks/keypad_door"
			}
		},
		{
			"weight": 1.0,
			"key": {
				"Type": "block",
				"Name": "securitycraft:blocks/keypad_frame"
			}
		},
		{
			"weight": 1.0,
			"key": {
				"Type": "block",
				"Name": "securitycraft:blocks/keypad_furnace"
			}
		},
		{
			"weight": 1.0,
			"key": {
				"Type": "block",
				"Name": "securitycraft:blocks/keypad_smoker"
			}
		},
		{
			"weight": 1.0,
			"key": {
				"Type": "block",
				"Name": "securitycraft:blocks/keypad_trapdoor"
			}
		},
		{
			"weight": 1.0,
			"key": {
				"Type": "block",
				"Name": "securitycraft:blocks/lapis_mine"
			}
		},
		{
			"weight": 1.0,
			"key": {
				"Type": "block",
				"Name": "securitycraft:blocks/laser_block"
			}
		},
		{
			"weight": 1.0,
			"key": {
				"Type": "block",
				"Name": "securitycraft:blocks/mine"
			}
		},
		{
			"weight": 1.0,
			"key": {
				"Type": "block",
				"Name": "securitycraft:blocks/motion_activated_light"
			}
		},
		{
			"weight": 1.0,
			"key": {
				"Type": "block",
				"Name": "securitycraft:blocks/nether_gold_mine"
			}
		},
		{
			"weight": 1.0,
			"key": {
				"Type": "block",
				"Name": "securitycraft:blocks/netherrack_mine"
			}
		},
		{
			"weight": 1.0,
			"key": {
				"Type": "block",
				"Name": "securitycraft:blocks/panic_button"
			}
		},
		{
			"weight": 1.0,
			"key": {
				"Type": "block",
				"Name": "securitycraft:blocks/portable_radar"
			}
		},
		{
			"weight": 1.0,
			"key": {
				"Type": "block",
				"Name": "securitycraft:blocks/projector"
			}
		},
		{
			"weight": 1.0,
			"key": {
				"Type": "block",
				"Name": "securitycraft:blocks/protecto"
			}
		},
		{
			"weight": 1.0,
			"key": {
				"Type": "block",
				"Name": "securitycraft:blocks/quartz_mine"
			}
		},
		{
			"weight": 1.0,
			"key": {
				"Type": "block",
				"Name": "securitycraft:blocks/redstone_mine"
			}
		},
		{
			"weight": 1.0,
			"key": {
				"Type": "block",
				"Name": "securitycraft:blocks/reinforced_acacia_button"
			}
		},
		{
			"weight": 1.0,
			"key": {
				"Type": "block",
				"Name": "securitycraft:blocks/reinforced_acacia_fence"
			}
		},
		{
			"weight": 1.0,
			"key": {
				"Type": "block",
				"Name": "securitycraft:blocks/reinforced_acacia_fence_gate"
			}
		},
		{
			"weight": 1.0,
			"key": {
				"Type": "block",
				"Name": "securitycraft:blocks/reinforced_acacia_log"
			}
		},
		{
			"weight": 1.0,
			"key": {
				"Type": "block",
				"Name": "securitycraft:blocks/reinforced_acacia_planks"
			}
		},
		{
			"weight": 1.0,
			"key": {
				"Type": "block",
				"Name": "securitycraft:blocks/reinforced_acacia_pressure_plate"
			}
		},
		{
			"weight": 1.0,
			"key": {
				"Type": "block",
				"Name": "securitycraft:blocks/reinforced_acacia_slab"
			}
		},
		{
			"weight": 1.0,
			"key": {
				"Type": "block",
				"Name": "securitycraft:blocks/reinforced_acacia_stairs"
			}
		},
		{
			"weight": 1.0,
			"key": {
				"Type": "block",
				"Name": "securitycraft:blocks/reinforced_acacia_wood"
			}
		},
		{
			"weight": 1.0,
			"key": {
				"Type": "block",
				"Name": "securitycraft:blocks/reinforced_amethyst_block"
			}
		},
		{
			"weight": 1.0,
			"key": {
				"Type": "block",
				"Name": "securitycraft:blocks/reinforced_andesite"
			}
		},
		{
			"weight": 1.0,
			"key": {
				"Type": "block",
				"Name": "securitycraft:blocks/reinforced_andesite_slab"
			}
		},
		{
			"weight": 1.0,
			"key": {
				"Type": "block",
				"Name": "securitycraft:blocks/reinforced_andesite_stairs"
			}
		},
		{
			"weight": 1.0,
			"key": {
				"Type": "block",
				"Name": "securitycraft:blocks/reinforced_andesite_wall"
			}
		},
		{
			"weight": 1.0,
			"key": {
				"Type": "block",
				"Name": "securitycraft:blocks/reinforced_bamboo_block"
			}
		},
		{
			"weight": 1.0,
			"key": {
				"Type": "block",
				"Name": "securitycraft:blocks/reinforced_bamboo_button"
			}
		},
		{
			"weight": 1.0,
			"key": {
				"Type": "block",
				"Name": "securitycraft:blocks/reinforced_bamboo_fence"
			}
		},
		{
			"weight": 1.0,
			"key": {
				"Type": "block",
				"Name": "securitycraft:blocks/reinforced_bamboo_fence_gate"
			}
		},
		{
			"weight": 1.0,
			"key": {
				"Type": "block",
				"Name": "securitycraft:blocks/reinforced_bamboo_mosaic"
			}
		},
		{
			"weight": 1.0,
			"key": {
				"Type": "block",
				"Name": "securitycraft:blocks/reinforced_bamboo_mosaic_slab"
			}
		},
		{
			"weight": 1.0,
			"key": {
				"Type": "block",
				"Name": "securitycraft:blocks/reinforced_bamboo_mosaic_stairs"
			}
		},
		{
			"weight": 1.0,
			"key": {
				"Type": "block",
				"Name": "securitycraft:blocks/reinforced_bamboo_planks"
			}
		},
		{
			"weight": 1.0,
			"key": {
				"Type": "block",
				"Name": "securitycraft:blocks/reinforced_bamboo_pressure_plate"
			}
		},
		{
			"weight": 1.0,
			"key": {
				"Type": "block",
				"Name": "securitycraft:blocks/reinforced_bamboo_slab"
			}
		},
		{
			"weight": 1.0,
			"key": {
				"Type": "block",
				"Name": "securitycraft:blocks/reinforced_bamboo_stairs"
			}
		},
		{
			"weight": 1.0,
			"key": {
				"Type": "block",
				"Name": "securitycraft:blocks/reinforced_basalt"
			}
		},
		{
			"weight": 1.0,
			"key": {
				"Type": "block",
				"Name": "securitycraft:blocks/reinforced_birch_button"
			}
		},
		{
			"weight": 1.0,
			"key": {
				"Type": "block",
				"Name": "securitycraft:blocks/reinforced_birch_fence"
			}
		},
		{
			"weight": 1.0,
			"key": {
				"Type": "block",
				"Name": "securitycraft:blocks/reinforced_birch_fence_gate"
			}
		},
		{
			"weight": 1.0,
			"key": {
				"Type": "block",
				"Name": "securitycraft:blocks/reinforced_birch_log"
			}
		},
		{
			"weight": 1.0,
			"key": {
				"Type": "block",
				"Name": "securitycraft:blocks/reinforced_birch_planks"
			}
		},
		{
			"weight": 1.0,
			"key": {
				"Type": "block",
				"Name": "securitycraft:blocks/reinforced_birch_pressure_plate"
			}
		},
		{
			"weight": 1.0,
			"key": {
				"Type": "block",
				"Name": "securitycraft:blocks/reinforced_birch_slab"
			}
		},
		{
			"weight": 1.0,
			"key": {
				"Type": "block",
				"Name": "securitycraft:blocks/reinforced_birch_stairs"
			}
		},
		{
			"weight": 1.0,
			"key": {
				"Type": "block",
				"Name": "securitycraft:blocks/reinforced_birch_wood"
			}
		},
		{
			"weight": 1.0,
			"key": {
				"Type": "block",
				"Name": "securitycraft:blocks/reinforced_black_carpet"
			}
		},
		{
			"weight": 1.0,
			"key": {
				"Type": "block",
				"Name": "securitycraft:blocks/reinforced_black_concrete"
			}
		},
		{
			"weight": 1.0,
			"key": {
				"Type": "block",
				"Name": "securitycraft:blocks/reinforced_black_glazed_terracotta"
			}
		},
		{
			"weight": 1.0,
			"key": {
				"Type": "block",
				"Name": "securitycraft:blocks/reinforced_black_stained_glass"
			}
		},
		{
			"weight": 1.0,
			"key": {
				"Type": "block",
				"Name": "securitycraft:blocks/reinforced_black_stained_glass_pane"
			}
		},
		{
			"weight": 1.0,
			"key": {
				"Type": "block",
				"Name": "securitycraft:blocks/reinforced_black_terracotta"
			}
		},
		{
			"weight": 1.0,
			"key": {
				"Type": "block",
				"Name": "securitycraft:blocks/reinforced_black_wool"
			}
		},
		{
			"weight": 1.0,
			"key": {
				"Type": "block",
				"Name": "securitycraft:blocks/reinforced_blackstone"
			}
		},
		{
			"weight": 1.0,
			"key": {
				"Type": "block",
				"Name": "securitycraft:blocks/reinforced_blackstone_slab"
			}
		},
		{
			"weight": 1.0,
			"key": {
				"Type": "block",
				"Name": "securitycraft:blocks/reinforced_blackstone_stairs"
			}
		},
		{
			"weight": 1.0,
			"key": {
				"Type": "block",
				"Name": "securitycraft:blocks/reinforced_blackstone_wall"
			}
		},
		{
			"weight": 1.0,
			"key": {
				"Type": "block",
				"Name": "securitycraft:blocks/reinforced_blue_carpet"
			}
		},
		{
			"weight": 1.0,
			"key": {
				"Type": "block",
				"Name": "securitycraft:blocks/reinforced_blue_concrete"
			}
		},
		{
			"weight": 1.0,
			"key": {
				"Type": "block",
				"Name": "securitycraft:blocks/reinforced_blue_glazed_terracotta"
			}
		},
		{
			"weight": 1.0,
			"key": {
				"Type": "block",
				"Name": "securitycraft:blocks/reinforced_blue_ice"
			}
		},
		{
			"weight": 1.0,
			"key": {
				"Type": "block",
				"Name": "securitycraft:blocks/reinforced_blue_stained_glass"
			}
		},
		{
			"weight": 1.0,
			"key": {
				"Type": "block",
				"Name": "securitycraft:blocks/reinforced_blue_stained_glass_pane"
			}
		},
		{
			"weight": 1.0,
			"key": {
				"Type": "block",
				"Name": "securitycraft:blocks/reinforced_blue_terracotta"
			}
		},
		{
			"weight": 1.0,
			"key": {
				"Type": "block",
				"Name": "securitycraft:blocks/reinforced_blue_wool"
			}
		},
		{
			"weight": 1.0,
			"key": {
				"Type": "block",
				"Name": "securitycraft:blocks/reinforced_bone_block"
			}
		},
		{
			"weight": 1.0,
			"key": {
				"Type": "block",
				"Name": "securitycraft:blocks/reinforced_bookshelf"
			}
		},
		{
			"weight": 1.0,
			"key": {
				"Type": "block",
				"Name": "securitycraft:blocks/reinforced_brick_slab"
			}
		},
		{
			"weight": 1.0,
			"key": {
				"Type": "block",
				"Name": "securitycraft:blocks/reinforced_brick_stairs"
			}
		},
		{
			"weight": 1.0,
			"key": {
				"Type": "block",
				"Name": "securitycraft:blocks/reinforced_brick_wall"
			}
		},
		{
			"weight": 1.0,
			"key": {
				"Type": "block",
				"Name": "securitycraft:blocks/reinforced_bricks"
			}
		},
		{
			"weight": 1.0,
			"key": {
				"Type": "block",
				"Name": "securitycraft:blocks/reinforced_brown_carpet"
			}
		},
		{
			"weight": 1.0,
			"key": {
				"Type": "block",
				"Name": "securitycraft:blocks/reinforced_brown_concrete"
			}
		},
		{
			"weight": 1.0,
			"key": {
				"Type": "block",
				"Name": "securitycraft:blocks/reinforced_brown_glazed_terracotta"
			}
		},
		{
			"weight": 1.0,
			"key": {
				"Type": "block",
				"Name": "securitycraft:blocks/reinforced_brown_stained_glass"
			}
		},
		{
			"weight": 1.0,
			"key": {
				"Type": "block",
				"Name": "securitycraft:blocks/reinforced_brown_stained_glass_pane"
			}
		},
		{
			"weight": 1.0,
			"key": {
				"Type": "block",
				"Name": "securitycraft:blocks/reinforced_brown_terracotta"
			}
		},
		{
			"weight": 1.0,
			"key": {
				"Type": "block",
				"Name": "securitycraft:blocks/reinforced_brown_wool"
			}
		},
		{
			"weight": 1.0,
			"key": {
				"Type": "block",
				"Name": "securitycraft:blocks/reinforced_calcite"
			}
		},
		{
			"weight": 1.0,
			"key": {
				"Type": "block",
				"Name": "securitycraft:blocks/reinforced_cauldron"
			}
		},
		{
			"weight": 1.0,
			"key": {
				"Type": "block",
				"Name": "securitycraft:blocks/reinforced_chain"
			}
		},
		{
			"weight": 1.0,
			"key": {
				"Type": "block",
				"Name": "securitycraft:blocks/reinforced_cherry_button"
			}
		},
		{
			"weight": 1.0,
			"key": {
				"Type": "block",
				"Name": "securitycraft:blocks/reinforced_cherry_fence"
			}
		},
		{
			"weight": 1.0,
			"key": {
				"Type": "block",
				"Name": "securitycraft:blocks/reinforced_cherry_fence_gate"
			}
		},
		{
			"weight": 1.0,
			"key": {
				"Type": "block",
				"Name": "securitycraft:blocks/reinforced_cherry_log"
			}
		},
		{
			"weight": 1.0,
			"key": {
				"Type": "block",
				"Name": "securitycraft:blocks/reinforced_cherry_planks"
			}
		},
		{
			"weight": 1.0,
			"key": {
				"Type": "block",
				"Name": "securitycraft:blocks/reinforced_cherry_pressure_plate"
			}
		},
		{
			"weight": 1.0,
			"key": {
				"Type": "block",
				"Name": "securitycraft:blocks/reinforced_cherry_slab"
			}
		},
		{
			"weight": 1.0,
			"key": {
				"Type": "block",
				"Name": "securitycraft:blocks/reinforced_cherry_stairs"
			}
		},
		{
			"weight": 1.0,
			"key": {
				"Type": "block",
				"Name": "securitycraft:blocks/reinforced_cherry_wood"
			}
		},
		{
			"weight": 1.0,
			"key": {
				"Type": "block",
				"Name": "securitycraft:blocks/reinforced_chiseled_bookshelf"
			}
		},
		{
			"weight": 1.0,
			"key": {
				"Type": "block",
				"Name": "securitycraft:blocks/reinforced_chiseled_copper"
			}
		},
		{
			"weight": 1.0,
			"key": {
				"Type": "block",
				"Name": "securitycraft:blocks/reinforced_chiseled_crystal_quartz_block"
			}
		},
		{
			"weight": 1.0,
			"key": {
				"Type": "block",
				"Name": "securitycraft:blocks/reinforced_chiseled_deepslate"
			}
		},
		{
			"weight": 1.0,
			"key": {
				"Type": "block",
				"Name": "securitycraft:blocks/reinforced_chiseled_nether_bricks"
			}
		},
		{
			"weight": 1.0,
			"key": {
				"Type": "block",
				"Name": "securitycraft:blocks/reinforced_chiseled_polished_blackstone"
			}
		},
		{
			"weight": 1.0,
			"key": {
				"Type": "block",
				"Name": "securitycraft:blocks/reinforced_chiseled_quartz_block"
			}
		},
		{
			"weight": 1.0,
			"key": {
				"Type": "block",
				"Name": "securitycraft:blocks/reinforced_chiseled_red_sandstone"
			}
		},
		{
			"weight": 1.0,
			"key": {
				"Type": "block",
				"Name": "securitycraft:blocks/reinforced_chiseled_sandstone"
			}
		},
		{
			"weight": 1.0,
			"key": {
				"Type": "block",
				"Name": "securitycraft:blocks/reinforced_chiseled_stone_bricks"
			}
		},
		{
			"weight": 1.0,
			"key": {
				"Type": "block",
				"Name": "securitycraft:blocks/reinforced_chiseled_tuff"
			}
		},
		{
			"weight": 1.0,
			"key": {
				"Type": "block",
				"Name": "securitycraft:blocks/reinforced_chiseled_tuff_bricks"
			}
		},
		{
			"weight": 1.0,
			"key": {
				"Type": "block",
				"Name": "securitycraft:blocks/reinforced_clay"
			}
		},
		{
			"weight": 1.0,
			"key": {
				"Type": "block",
				"Name": "securitycraft:blocks/reinforced_coal_block"
			}
		},
		{
			"weight": 1.0,
			"key": {
				"Type": "block",
				"Name": "securitycraft:blocks/reinforced_coarse_dirt"
			}
		},
		{
			"weight": 1.0,
			"key": {
				"Type": "block",
				"Name": "securitycraft:blocks/reinforced_cobbled_deepslate"
			}
		},
		{
			"weight": 1.0,
			"key": {
				"Type": "block",
				"Name": "securitycraft:blocks/reinforced_cobbled_deepslate_slab"
			}
		},
		{
			"weight": 1.0,
			"key": {
				"Type": "block",
				"Name": "securitycraft:blocks/reinforced_cobbled_deepslate_stairs"
			}
		},
		{
			"weight": 1.0,
			"key": {
				"Type": "block",
				"Name": "securitycraft:blocks/reinforced_cobbled_deepslate_wall"
			}
		},
		{
			"weight": 1.0,
			"key": {
				"Type": "block",
				"Name": "securitycraft:blocks/reinforced_cobblestone"
			}
		},
		{
			"weight": 1.0,
			"key": {
				"Type": "block",
				"Name": "securitycraft:blocks/reinforced_cobblestone_slab"
			}
		},
		{
			"weight": 1.0,
			"key": {
				"Type": "block",
				"Name": "securitycraft:blocks/reinforced_cobblestone_stairs"
			}
		},
		{
			"weight": 1.0,
			"key": {
				"Type": "block",
				"Name": "securitycraft:blocks/reinforced_cobblestone_wall"
			}
		},
		{
			"weight": 1.0,
			"key": {
				"Type": "block",
				"Name": "securitycraft:blocks/reinforced_cobweb"
			}
		},
		{
			"weight": 1.0,
			"key": {
				"Type": "block",
				"Name": "securitycraft:blocks/reinforced_copper_block"
			}
		},
		{
			"weight": 1.0,
			"key": {
				"Type": "block",
				"Name": "securitycraft:blocks/reinforced_copper_bulb"
			}
		},
		{
			"weight": 1.0,
			"key": {
				"Type": "block",
				"Name": "securitycraft:blocks/reinforced_copper_grate"
			}
		},
		{
			"weight": 1.0,
			"key": {
				"Type": "block",
				"Name": "securitycraft:blocks/reinforced_cracked_deepslate_bricks"
			}
		},
		{
			"weight": 1.0,
			"key": {
				"Type": "block",
				"Name": "securitycraft:blocks/reinforced_cracked_deepslate_tiles"
			}
		},
		{
			"weight": 1.0,
			"key": {
				"Type": "block",
				"Name": "securitycraft:blocks/reinforced_cracked_nether_bricks"
			}
		},
		{
			"weight": 1.0,
			"key": {
				"Type": "block",
				"Name": "securitycraft:blocks/reinforced_cracked_polished_blackstone_bricks"
			}
		},
		{
			"weight": 1.0,
			"key": {
				"Type": "block",
				"Name": "securitycraft:blocks/reinforced_cracked_stone_bricks"
			}
		},
		{
			"weight": 1.0,
			"key": {
				"Type": "block",
				"Name": "securitycraft:blocks/reinforced_crimson_button"
			}
		},
		{
			"weight": 1.0,
			"key": {
				"Type": "block",
				"Name": "securitycraft:blocks/reinforced_crimson_fence"
			}
		},
		{
			"weight": 1.0,
			"key": {
				"Type": "block",
				"Name": "securitycraft:blocks/reinforced_crimson_fence_gate"
			}
		},
		{
			"weight": 1.0,
			"key": {
				"Type": "block",
				"Name": "securitycraft:blocks/reinforced_crimson_hyphae"
			}
		},
		{
			"weight": 1.0,
			"key": {
				"Type": "block",
				"Name": "securitycraft:blocks/reinforced_crimson_nylium"
			}
		},
		{
			"weight": 1.0,
			"key": {
				"Type": "block",
				"Name": "securitycraft:blocks/reinforced_crimson_planks"
			}
		},
		{
			"weight": 1.0,
			"key": {
				"Type": "block",
				"Name": "securitycraft:blocks/reinforced_crimson_pressure_plate"
			}
		},
		{
			"weight": 1.0,
			"key": {
				"Type": "block",
				"Name": "securitycraft:blocks/reinforced_crimson_slab"
			}
		},
		{
			"weight": 1.0,
			"key": {
				"Type": "block",
				"Name": "securitycraft:blocks/reinforced_crimson_stairs"
			}
		},
		{
			"weight": 1.0,
			"key": {
				"Type": "block",
				"Name": "securitycraft:blocks/reinforced_crimson_stem"
			}
		},
		{
			"weight": 1.0,
			"key": {
				"Type": "block",
				"Name": "securitycraft:blocks/reinforced_crying_obsidian"
			}
		},
		{
			"weight": 1.0,
			"key": {
				"Type": "block",
				"Name": "securitycraft:blocks/reinforced_crystal_quartz_block"
			}
		},
		{
			"weight": 1.0,
			"key": {
				"Type": "block",
				"Name": "securitycraft:blocks/reinforced_crystal_quartz_bricks"
			}
		},
		{
			"weight": 1.0,
			"key": {
				"Type": "block",
				"Name": "securitycraft:blocks/reinforced_crystal_quartz_pillar"
			}
		},
		{
			"weight": 1.0,
			"key": {
				"Type": "block",
				"Name": "securitycraft:blocks/reinforced_crystal_quartz_slab"
			}
		},
		{
			"weight": 1.0,
			"key": {
				"Type": "block",
				"Name": "securitycraft:blocks/reinforced_crystal_quartz_stairs"
			}
		},
		{
			"weight": 1.0,
			"key": {
				"Type": "block",
				"Name": "securitycraft:blocks/reinforced_cut_copper"
			}
		},
		{
			"weight": 1.0,
			"key": {
				"Type": "block",
				"Name": "securitycraft:blocks/reinforced_cut_copper_slab"
			}
		},
		{
			"weight": 1.0,
			"key": {
				"Type": "block",
				"Name": "securitycraft:blocks/reinforced_cut_copper_stairs"
			}
		},
		{
			"weight": 1.0,
			"key": {
				"Type": "block",
				"Name": "securitycraft:blocks/reinforced_cut_red_sandstone"
			}
		},
		{
			"weight": 1.0,
			"key": {
				"Type": "block",
				"Name": "securitycraft:blocks/reinforced_cut_red_sandstone_slab"
			}
		},
		{
			"weight": 1.0,
			"key": {
				"Type": "block",
				"Name": "securitycraft:blocks/reinforced_cut_sandstone"
			}
		},
		{
			"weight": 1.0,
			"key": {
				"Type": "block",
				"Name": "securitycraft:blocks/reinforced_cut_sandstone_slab"
			}
		},
		{
			"weight": 1.0,
			"key": {
				"Type": "block",
				"Name": "securitycraft:blocks/reinforced_cyan_carpet"
			}
		},
		{
			"weight": 1.0,
			"key": {
				"Type": "block",
				"Name": "securitycraft:blocks/reinforced_cyan_concrete"
			}
		},
		{
			"weight": 1.0,
			"key": {
				"Type": "block",
				"Name": "securitycraft:blocks/reinforced_cyan_glazed_terracotta"
			}
		},
		{
			"weight": 1.0,
			"key": {
				"Type": "block",
				"Name": "securitycraft:blocks/reinforced_cyan_stained_glass"
			}
		},
		{
			"weight": 1.0,
			"key": {
				"Type": "block",
				"Name": "securitycraft:blocks/reinforced_cyan_stained_glass_pane"
			}
		},
		{
			"weight": 1.0,
			"key": {
				"Type": "block",
				"Name": "securitycraft:blocks/reinforced_cyan_terracotta"
			}
		},
		{
			"weight": 1.0,
			"key": {
				"Type": "block",
				"Name": "securitycraft:blocks/reinforced_cyan_wool"
			}
		},
		{
			"weight": 1.0,
			"key": {
				"Type": "block",
				"Name": "securitycraft:blocks/reinforced_dark_oak_button"
			}
		},
		{
			"weight": 1.0,
			"key": {
				"Type": "block",
				"Name": "securitycraft:blocks/reinforced_dark_oak_fence"
			}
		},
		{
			"weight": 1.0,
			"key": {
				"Type": "block",
				"Name": "securitycraft:blocks/reinforced_dark_oak_fence_gate"
			}
		},
		{
			"weight": 1.0,
			"key": {
				"Type": "block",
				"Name": "securitycraft:blocks/reinforced_dark_oak_log"
			}
		},
		{
			"weight": 1.0,
			"key": {
				"Type": "block",
				"Name": "securitycraft:blocks/reinforced_dark_oak_planks"
			}
		},
		{
			"weight": 1.0,
			"key": {
				"Type": "block",
				"Name": "securitycraft:blocks/reinforced_dark_oak_pressure_plate"
			}
		},
		{
			"weight": 1.0,
			"key": {
				"Type": "block",
				"Name": "securitycraft:blocks/reinforced_dark_oak_slab"
			}
		},
		{
			"weight": 1.0,
			"key": {
				"Type": "block",
				"Name": "securitycraft:blocks/reinforced_dark_oak_stairs"
			}
		},
		{
			"weight": 1.0,
			"key": {
				"Type": "block",
				"Name": "securitycraft:blocks/reinforced_dark_oak_wood"
			}
		},
		{
			"weight": 1.0,
			"key": {
				"Type": "block",
				"Name": "securitycraft:blocks/reinforced_dark_prismarine"
			}
		},
		{
			"weight": 1.0,
			"key": {
				"Type": "block",
				"Name": "securitycraft:blocks/reinforced_dark_prismarine_slab"
			}
		},
		{
			"weight": 1.0,
			"key": {
				"Type": "block",
				"Name": "securitycraft:blocks/reinforced_dark_prismarine_stairs"
			}
		},
		{
			"weight": 1.0,
			"key": {
				"Type": "block",
				"Name": "securitycraft:blocks/reinforced_deepslate"
			}
		},
		{
			"weight": 1.0,
			"key": {
				"Type": "block",
				"Name": "securitycraft:blocks/reinforced_deepslate_brick_slab"
			}
		},
		{
			"weight": 1.0,
			"key": {
				"Type": "block",
				"Name": "securitycraft:blocks/reinforced_deepslate_brick_stairs"
			}
		},
		{
			"weight": 1.0,
			"key": {
				"Type": "block",
				"Name": "securitycraft:blocks/reinforced_deepslate_brick_wall"
			}
		},
		{
			"weight": 1.0,
			"key": {
				"Type": "block",
				"Name": "securitycraft:blocks/reinforced_deepslate_bricks"
			}
		},
		{
			"weight": 1.0,
			"key": {
				"Type": "block",
				"Name": "securitycraft:blocks/reinforced_deepslate_tile_slab"
			}
		},
		{
			"weight": 1.0,
			"key": {
				"Type": "block",
				"Name": "securitycraft:blocks/reinforced_deepslate_tile_stairs"
			}
		},
		{
			"weight": 1.0,
			"key": {
				"Type": "block",
				"Name": "securitycraft:blocks/reinforced_deepslate_tile_wall"
			}
		},
		{
			"weight": 1.0,
			"key": {
				"Type": "block",
				"Name": "securitycraft:blocks/reinforced_deepslate_tiles"
			}
		},
		{
			"weight": 1.0,
			"key": {
				"Type": "block",
				"Name": "securitycraft:blocks/reinforced_diamond_block"
			}
		},
		{
			"weight": 1.0,
			"key": {
				"Type": "block",
				"Name": "securitycraft:blocks/reinforced_diorite"
			}
		},
		{
			"weight": 1.0,
			"key": {
				"Type": "block",
				"Name": "securitycraft:blocks/reinforced_diorite_slab"
			}
		},
		{
			"weight": 1.0,
			"key": {
				"Type": "block",
				"Name": "securitycraft:blocks/reinforced_diorite_stairs"
			}
		},
		{
			"weight": 1.0,
			"key": {
				"Type": "block",
				"Name": "securitycraft:blocks/reinforced_diorite_wall"
			}
		},
		{
			"weight": 1.0,
			"key": {
				"Type": "block",
				"Name": "securitycraft:blocks/reinforced_dirt"
			}
		},
		{
			"weight": 1.0,
			"key": {
				"Type": "block",
				"Name": "securitycraft:blocks/reinforced_dispenser"
			}
		},
		{
			"weight": 1.0,
			"key": {
				"Type": "block",
				"Name": "securitycraft:blocks/reinforced_dripstone_block"
			}
		},
		{
			"weight": 1.0,
			"key": {
				"Type": "block",
				"Name": "securitycraft:blocks/reinforced_dropper"
			}
		},
		{
			"weight": 1.0,
			"key": {
				"Type": "block",
				"Name": "securitycraft:blocks/reinforced_emerald_block"
			}
		},
		{
			"weight": 1.0,
			"key": {
				"Type": "block",
				"Name": "securitycraft:blocks/reinforced_end_rod"
			}
		},
		{
			"weight": 1.0,
			"key": {
				"Type": "block",
				"Name": "securitycraft:blocks/reinforced_end_stone"
			}
		},
		{
			"weight": 1.0,
			"key": {
				"Type": "block",
				"Name": "securitycraft:blocks/reinforced_end_stone_brick_slab"
			}
		},
		{
			"weight": 1.0,
			"key": {
				"Type": "block",
				"Name": "securitycraft:blocks/reinforced_end_stone_brick_stairs"
			}
		},
		{
			"weight": 1.0,
			"key": {
				"Type": "block",
				"Name": "securitycraft:blocks/reinforced_end_stone_brick_wall"
			}
		},
		{
			"weight": 1.0,
			"key": {
				"Type": "block",
				"Name": "securitycraft:blocks/reinforced_end_stone_bricks"
			}
		},
		{
			"weight": 1.0,
			"key": {
				"Type": "block",
				"Name": "securitycraft:blocks/reinforced_exposed_chiseled_copper"
			}
		},
		{
			"weight": 1.0,
			"key": {
				"Type": "block",
				"Name": "securitycraft:blocks/reinforced_exposed_copper"
			}
		},
		{
			"weight": 1.0,
			"key": {
				"Type": "block",
				"Name": "securitycraft:blocks/reinforced_exposed_copper_bulb"
			}
		},
		{
			"weight": 1.0,
			"key": {
				"Type": "block",
				"Name": "securitycraft:blocks/reinforced_exposed_copper_grate"
			}
		},
		{
			"weight": 1.0,
			"key": {
				"Type": "block",
				"Name": "securitycraft:blocks/reinforced_exposed_cut_copper"
			}
		},
		{
			"weight": 1.0,
			"key": {
				"Type": "block",
				"Name": "securitycraft:blocks/reinforced_exposed_cut_copper_slab"
			}
		},
		{
			"weight": 1.0,
			"key": {
				"Type": "block",
				"Name": "securitycraft:blocks/reinforced_exposed_cut_copper_stairs"
			}
		},
		{
			"weight": 1.0,
			"key": {
				"Type": "block",
				"Name": "securitycraft:blocks/reinforced_fence_gate"
			}
		},
		{
			"weight": 1.0,
			"key": {
				"Type": "block",
				"Name": "securitycraft:blocks/reinforced_glass"
			}
		},
		{
			"weight": 1.0,
			"key": {
				"Type": "block",
				"Name": "securitycraft:blocks/reinforced_glass_pane"
			}
		},
		{
			"weight": 1.0,
			"key": {
				"Type": "block",
				"Name": "securitycraft:blocks/reinforced_glowstone"
			}
		},
		{
			"weight": 1.0,
			"key": {
				"Type": "block",
				"Name": "securitycraft:blocks/reinforced_gold_block"
			}
		},
		{
			"weight": 1.0,
			"key": {
				"Type": "block",
				"Name": "securitycraft:blocks/reinforced_granite"
			}
		},
		{
			"weight": 1.0,
			"key": {
				"Type": "block",
				"Name": "securitycraft:blocks/reinforced_granite_slab"
			}
		},
		{
			"weight": 1.0,
			"key": {
				"Type": "block",
				"Name": "securitycraft:blocks/reinforced_granite_stairs"
			}
		},
		{
			"weight": 1.0,
			"key": {
				"Type": "block",
				"Name": "securitycraft:blocks/reinforced_granite_wall"
			}
		},
		{
			"weight": 1.0,
			"key": {
				"Type": "block",
				"Name": "securitycraft:blocks/reinforced_grass_block"
			}
		},
		{
			"weight": 1.0,
			"key": {
				"Type": "block",
				"Name": "securitycraft:blocks/reinforced_grass_path"
			}
		},
		{
			"weight": 1.0,
			"key": {
				"Type": "block",
				"Name": "securitycraft:blocks/reinforced_gravel"
			}
		},
		{
			"weight": 1.0,
			"key": {
				"Type": "block",
				"Name": "securitycraft:blocks/reinforced_gray_carpet"
			}
		},
		{
			"weight": 1.0,
			"key": {
				"Type": "block",
				"Name": "securitycraft:blocks/reinforced_gray_concrete"
			}
		},
		{
			"weight": 1.0,
			"key": {
				"Type": "block",
				"Name": "securitycraft:blocks/reinforced_gray_glazed_terracotta"
			}
		},
		{
			"weight": 1.0,
			"key": {
				"Type": "block",
				"Name": "securitycraft:blocks/reinforced_gray_stained_glass"
			}
		},
		{
			"weight": 1.0,
			"key": {
				"Type": "block",
				"Name": "securitycraft:blocks/reinforced_gray_stained_glass_pane"
			}
		},
		{
			"weight": 1.0,
			"key": {
				"Type": "block",
				"Name": "securitycraft:blocks/reinforced_gray_terracotta"
			}
		},
		{
			"weight": 1.0,
			"key": {
				"Type": "block",
				"Name": "securitycraft:blocks/reinforced_gray_wool"
			}
		},
		{
			"weight": 1.0,
			"key": {
				"Type": "block",
				"Name": "securitycraft:blocks/reinforced_green_carpet"
			}
		},
		{
			"weight": 1.0,
			"key": {
				"Type": "block",
				"Name": "securitycraft:blocks/reinforced_green_concrete"
			}
		},
		{
			"weight": 1.0,
			"key": {
				"Type": "block",
				"Name": "securitycraft:blocks/reinforced_green_glazed_terracotta"
			}
		},
		{
			"weight": 1.0,
			"key": {
				"Type": "block",
				"Name": "securitycraft:blocks/reinforced_green_stained_glass"
			}
		},
		{
			"weight": 1.0,
			"key": {
				"Type": "block",
				"Name": "securitycraft:blocks/reinforced_green_stained_glass_pane"
			}
		},
		{
			"weight": 1.0,
			"key": {
				"Type": "block",
				"Name": "securitycraft:blocks/reinforced_green_terracotta"
			}
		},
		{
			"weight": 1.0,
			"key": {
				"Type": "block",
				"Name": "securitycraft:blocks/reinforced_green_wool"
			}
		},
		{
			"weight": 1.0,
			"key": {
				"Type": "block",
				"Name": "securitycraft:blocks/reinforced_hardened_clay"
			}
		},
		{
			"weight": 1.0,
			"key": {
				"Type": "block",
				"Name": "securitycraft:blocks/reinforced_hopper"
			}
		},
		{
			"weight": 1.0,
			"key": {
				"Type": "block",
				"Name": "securitycraft:blocks/reinforced_ice"
			}
		},
		{
			"weight": 1.0,
			"key": {
				"Type": "block",
				"Name": "securitycraft:blocks/reinforced_iron_bars"
			}
		},
		{
			"weight": 1.0,
			"key": {
				"Type": "block",
				"Name": "securitycraft:blocks/reinforced_iron_block"
			}
		},
		{
			"weight": 1.0,
			"key": {
				"Type": "block",
				"Name": "securitycraft:blocks/reinforced_iron_trapdoor"
			}
		},
		{
			"weight": 1.0,
			"key": {
				"Type": "block",
				"Name": "securitycraft:blocks/reinforced_jungle_button"
			}
		},
		{
			"weight": 1.0,
			"key": {
				"Type": "block",
				"Name": "securitycraft:blocks/reinforced_jungle_fence"
			}
		},
		{
			"weight": 1.0,
			"key": {
				"Type": "block",
				"Name": "securitycraft:blocks/reinforced_jungle_fence_gate"
			}
		},
		{
			"weight": 1.0,
			"key": {
				"Type": "block",
				"Name": "securitycraft:blocks/reinforced_jungle_log"
			}
		},
		{
			"weight": 1.0,
			"key": {
				"Type": "block",
				"Name": "securitycraft:blocks/reinforced_jungle_planks"
			}
		},
		{
			"weight": 1.0,
			"key": {
				"Type": "block",
				"Name": "securitycraft:blocks/reinforced_jungle_pressure_plate"
			}
		},
		{
			"weight": 1.0,
			"key": {
				"Type": "block",
				"Name": "securitycraft:blocks/reinforced_jungle_slab"
			}
		},
		{
			"weight": 1.0,
			"key": {
				"Type": "block",
				"Name": "securitycraft:blocks/reinforced_jungle_stairs"
			}
		},
		{
			"weight": 1.0,
			"key": {
				"Type": "block",
				"Name": "securitycraft:blocks/reinforced_jungle_wood"
			}
		},
		{
			"weight": 1.0,
			"key": {
				"Type": "block",
				"Name": "securitycraft:blocks/reinforced_ladder"
			}
		},
		{
			"weight": 1.0,
			"key": {
				"Type": "block",
				"Name": "securitycraft:blocks/reinforced_lantern"
			}
		},
		{
			"weight": 1.0,
			"key": {
				"Type": "block",
				"Name": "securitycraft:blocks/reinforced_lapis_block"
			}
		},
		{
			"weight": 1.0,
			"key": {
				"Type": "block",
				"Name": "securitycraft:blocks/reinforced_lava_cauldron"
			}
		},
		{
			"weight": 1.0,
			"key": {
				"Type": "block",
				"Name": "securitycraft:blocks/reinforced_lectern"
			}
		},
		{
			"weight": 1.0,
			"key": {
				"Type": "block",
				"Name": "securitycraft:blocks/reinforced_lever"
			}
		},
		{
			"weight": 1.0,
			"key": {
				"Type": "block",
				"Name": "securitycraft:blocks/reinforced_light_blue_carpet"
			}
		},
		{
			"weight": 1.0,
			"key": {
				"Type": "block",
				"Name": "securitycraft:blocks/reinforced_light_blue_concrete"
			}
		},
		{
			"weight": 1.0,
			"key": {
				"Type": "block",
				"Name": "securitycraft:blocks/reinforced_light_blue_glazed_terracotta"
			}
		},
		{
			"weight": 1.0,
			"key": {
				"Type": "block",
				"Name": "securitycraft:blocks/reinforced_light_blue_stained_glass"
			}
		},
		{
			"weight": 1.0,
			"key": {
				"Type": "block",
				"Name": "securitycraft:blocks/reinforced_light_blue_stained_glass_pane"
			}
		},
		{
			"weight": 1.0,
			"key": {
				"Type": "block",
				"Name": "securitycraft:blocks/reinforced_light_blue_terracotta"
			}
		},
		{
			"weight": 1.0,
			"key": {
				"Type": "block",
				"Name": "securitycraft:blocks/reinforced_light_blue_wool"
			}
		},
		{
			"weight": 1.0,
			"key": {
				"Type": "block",
				"Name": "securitycraft:blocks/reinforced_light_gray_carpet"
			}
		},
		{
			"weight": 1.0,
			"key": {
				"Type": "block",
				"Name": "securitycraft:blocks/reinforced_light_gray_concrete"
			}
		},
		{
			"weight": 1.0,
			"key": {
				"Type": "block",
				"Name": "securitycraft:blocks/reinforced_light_gray_glazed_terracotta"
			}
		},
		{
			"weight": 1.0,
			"key": {
				"Type": "block",
				"Name": "securitycraft:blocks/reinforced_light_gray_stained_glass"
			}
		},
		{
			"weight": 1.0,
			"key": {
				"Type": "block",
				"Name": "securitycraft:blocks/reinforced_light_gray_stained_glass_pane"
			}
		},
		{
			"weight": 1.0,
			"key": {
				"Type": "block",
				"Name": "securitycraft:blocks/reinforced_light_gray_terracotta"
			}
		},
		{
			"weight": 1.0,
			"key": {
				"Type": "block",
				"Name": "securitycraft:blocks/reinforced_light_gray_wool"
			}
		},
		{
			"weight": 1.0,
			"key": {
				"Type": "block",
				"Name": "securitycraft:blocks/reinforced_lime_carpet"
			}
		},
		{
			"weight": 1.0,
			"key": {
				"Type": "block",
				"Name": "securitycraft:blocks/reinforced_lime_concrete"
			}
		},
		{
			"weight": 1.0,
			"key": {
				"Type": "block",
				"Name": "securitycraft:blocks/reinforced_lime_glazed_terracotta"
			}
		},
		{
			"weight": 1.0,
			"key": {
				"Type": "block",
				"Name": "securitycraft:blocks/reinforced_lime_stained_glass"
			}
		},
		{
			"weight": 1.0,
			"key": {
				"Type": "block",
				"Name": "securitycraft:blocks/reinforced_lime_stained_glass_pane"
			}
		},
		{
			"weight": 1.0,
			"key": {
				"Type": "block",
				"Name": "securitycraft:blocks/reinforced_lime_terracotta"
			}
		},
		{
			"weight": 1.0,
			"key": {
				"Type": "block",
				"Name": "securitycraft:blocks/reinforced_lime_wool"
			}
		},
		{
			"weight": 1.0,
			"key": {
				"Type": "block",
				"Name": "securitycraft:blocks/reinforced_magenta_carpet"
			}
		},
		{
			"weight": 1.0,
			"key": {
				"Type": "block",
				"Name": "securitycraft:blocks/reinforced_magenta_concrete"
			}
		},
		{
			"weight": 1.0,
			"key": {
				"Type": "block",
				"Name": "securitycraft:blocks/reinforced_magenta_glazed_terracotta"
			}
		},
		{
			"weight": 1.0,
			"key": {
				"Type": "block",
				"Name": "securitycraft:blocks/reinforced_magenta_stained_glass"
			}
		},
		{
			"weight": 1.0,
			"key": {
				"Type": "block",
				"Name": "securitycraft:blocks/reinforced_magenta_stained_glass_pane"
			}
		},
		{
			"weight": 1.0,
			"key": {
				"Type": "block",
				"Name": "securitycraft:blocks/reinforced_magenta_terracotta"
			}
		},
		{
			"weight": 1.0,
			"key": {
				"Type": "block",
				"Name": "securitycraft:blocks/reinforced_magenta_wool"
			}
		},
		{
			"weight": 1.0,
			"key": {
				"Type": "block",
				"Name": "securitycraft:blocks/reinforced_magma_block"
			}
		},
		{
			"weight": 1.0,
			"key": {
				"Type": "block",
				"Name": "securitycraft:blocks/reinforced_mangrove_button"
			}
		},
		{
			"weight": 1.0,
			"key": {
				"Type": "block",
				"Name": "securitycraft:blocks/reinforced_mangrove_fence"
			}
		},
		{
			"weight": 1.0,
			"key": {
				"Type": "block",
				"Name": "securitycraft:blocks/reinforced_mangrove_fence_gate"
			}
		},
		{
			"weight": 1.0,
			"key": {
				"Type": "block",
				"Name": "securitycraft:blocks/reinforced_mangrove_log"
			}
		},
		{
			"weight": 1.0,
			"key": {
				"Type": "block",
				"Name": "securitycraft:blocks/reinforced_mangrove_planks"
			}
		},
		{
			"weight": 1.0,
			"key": {
				"Type": "block",
				"Name": "securitycraft:blocks/reinforced_mangrove_pressure_plate"
			}
		},
		{
			"weight": 1.0,
			"key": {
				"Type": "block",
				"Name": "securitycraft:blocks/reinforced_mangrove_slab"
			}
		},
		{
			"weight": 1.0,
			"key": {
				"Type": "block",
				"Name": "securitycraft:blocks/reinforced_mangrove_stairs"
			}
		},
		{
			"weight": 1.0,
			"key": {
				"Type": "block",
				"Name": "securitycraft:blocks/reinforced_mangrove_wood"
			}
		},
		{
			"weight": 1.0,
			"key": {
				"Type": "block",
				"Name": "securitycraft:blocks/reinforced_moss_block"
			}
		},
		{
			"weight": 1.0,
			"key": {
				"Type": "block",
				"Name": "securitycraft:blocks/reinforced_moss_carpet"
			}
		},
		{
			"weight": 1.0,
			"key": {
				"Type": "block",
				"Name": "securitycraft:blocks/reinforced_mossy_cobblestone"
			}
		},
		{
			"weight": 1.0,
			"key": {
				"Type": "block",
				"Name": "securitycraft:blocks/reinforced_mossy_cobblestone_slab"
			}
		},
		{
			"weight": 1.0,
			"key": {
				"Type": "block",
				"Name": "securitycraft:blocks/reinforced_mossy_cobblestone_stairs"
			}
		},
		{
			"weight": 1.0,
			"key": {
				"Type": "block",
				"Name": "securitycraft:blocks/reinforced_mossy_cobblestone_wall"
			}
		},
		{
			"weight": 1.0,
			"key": {
				"Type": "block",
				"Name": "securitycraft:blocks/reinforced_mossy_stone_brick_slab"
			}
		},
		{
			"weight": 1.0,
			"key": {
				"Type": "block",
				"Name": "securitycraft:blocks/reinforced_mossy_stone_brick_stairs"
			}
		},
		{
			"weight": 1.0,
			"key": {
				"Type": "block",
				"Name": "securitycraft:blocks/reinforced_mossy_stone_brick_wall"
			}
		},
		{
			"weight": 1.0,
			"key": {
				"Type": "block",
				"Name": "securitycraft:blocks/reinforced_mossy_stone_bricks"
			}
		},
		{
			"weight": 1.0,
			"key": {
				"Type": "block",
				"Name": "securitycraft:blocks/reinforced_mud"
			}
		},
		{
			"weight": 1.0,
			"key": {
				"Type": "block",
				"Name": "securitycraft:blocks/reinforced_mud_brick_slab"
			}
		},
		{
			"weight": 1.0,
			"key": {
				"Type": "block",
				"Name": "securitycraft:blocks/reinforced_mud_brick_stairs"
			}
		},
		{
			"weight": 1.0,
			"key": {
				"Type": "block",
				"Name": "securitycraft:blocks/reinforced_mud_brick_wall"
			}
		},
		{
			"weight": 1.0,
			"key": {
				"Type": "block",
				"Name": "securitycraft:blocks/reinforced_mud_bricks"
			}
		},
		{
			"weight": 1.0,
			"key": {
				"Type": "block",
				"Name": "securitycraft:blocks/reinforced_mycelium"
			}
		},
		{
			"weight": 1.0,
			"key": {
				"Type": "block",
				"Name": "securitycraft:blocks/reinforced_nether_brick_fence"
			}
		},
		{
			"weight": 1.0,
			"key": {
				"Type": "block",
				"Name": "securitycraft:blocks/reinforced_nether_brick_slab"
			}
		},
		{
			"weight": 1.0,
			"key": {
				"Type": "block",
				"Name": "securitycraft:blocks/reinforced_nether_brick_stairs"
			}
		},
		{
			"weight": 1.0,
			"key": {
				"Type": "block",
				"Name": "securitycraft:blocks/reinforced_nether_brick_wall"
			}
		},
		{
			"weight": 1.0,
			"key": {
				"Type": "block",
				"Name": "securitycraft:blocks/reinforced_nether_bricks"
			}
		},
		{
			"weight": 1.0,
			"key": {
				"Type": "block",
				"Name": "securitycraft:blocks/reinforced_nether_wart_block"
			}
		},
		{
			"weight": 1.0,
			"key": {
				"Type": "block",
				"Name": "securitycraft:blocks/reinforced_netherite_block"
			}
		},
		{
			"weight": 1.0,
			"key": {
				"Type": "block",
				"Name": "securitycraft:blocks/reinforced_netherrack"
			}
		},
		{
			"weight": 1.0,
			"key": {
				"Type": "block",
				"Name": "securitycraft:blocks/reinforced_normal_stone_slab"
			}
		},
		{
			"weight": 1.0,
			"key": {
				"Type": "block",
				"Name": "securitycraft:blocks/reinforced_oak_button"
			}
		},
		{
			"weight": 1.0,
			"key": {
				"Type": "block",
				"Name": "securitycraft:blocks/reinforced_oak_fence"
			}
		},
		{
			"weight": 1.0,
			"key": {
				"Type": "block",
				"Name": "securitycraft:blocks/reinforced_oak_fence_gate"
			}
		},
		{
			"weight": 1.0,
			"key": {
				"Type": "block",
				"Name": "securitycraft:blocks/reinforced_oak_log"
			}
		},
		{
			"weight": 1.0,
			"key": {
				"Type": "block",
				"Name": "securitycraft:blocks/reinforced_oak_planks"
			}
		},
		{
			"weight": 1.0,
			"key": {
				"Type": "block",
				"Name": "securitycraft:blocks/reinforced_oak_pressure_plate"
			}
		},
		{
			"weight": 1.0,
			"key": {
				"Type": "block",
				"Name": "securitycraft:blocks/reinforced_oak_slab"
			}
		},
		{
			"weight": 1.0,
			"key": {
				"Type": "block",
				"Name": "securitycraft:blocks/reinforced_oak_stairs"
			}
		},
		{
			"weight": 1.0,
			"key": {
				"Type": "block",
				"Name": "securitycraft:blocks/reinforced_oak_wood"
			}
		},
		{
			"weight": 1.0,
			"key": {
				"Type": "block",
				"Name": "securitycraft:blocks/reinforced_observer"
			}
		},
		{
			"weight": 1.0,
			"key": {
				"Type": "block",
				"Name": "securitycraft:blocks/reinforced_obsidian"
			}
		},
		{
			"weight": 1.0,
			"key": {
				"Type": "block",
				"Name": "securitycraft:blocks/reinforced_ochre_froglight"
			}
		},
		{
			"weight": 1.0,
			"key": {
				"Type": "block",
				"Name": "securitycraft:blocks/reinforced_orange_carpet"
			}
		},
		{
			"weight": 1.0,
			"key": {
				"Type": "block",
				"Name": "securitycraft:blocks/reinforced_orange_concrete"
			}
		},
		{
			"weight": 1.0,
			"key": {
				"Type": "block",
				"Name": "securitycraft:blocks/reinforced_orange_glazed_terracotta"
			}
		},
		{
			"weight": 1.0,
			"key": {
				"Type": "block",
				"Name": "securitycraft:blocks/reinforced_orange_stained_glass"
			}
		},
		{
			"weight": 1.0,
			"key": {
				"Type": "block",
				"Name": "securitycraft:blocks/reinforced_orange_stained_glass_pane"
			}
		},
		{
			"weight": 1.0,
			"key": {
				"Type": "block",
				"Name": "securitycraft:blocks/reinforced_orange_terracotta"
			}
		},
		{
			"weight": 1.0,
			"key": {
				"Type": "block",
				"Name": "securitycraft:blocks/reinforced_orange_wool"
			}
		},
		{
			"weight": 1.0,
			"key": {
				"Type": "block",
				"Name": "securitycraft:blocks/reinforced_oxidized_chiseled_copper"
			}
		},
		{
			"weight": 1.0,
			"key": {
				"Type": "block",
				"Name": "securitycraft:blocks/reinforced_oxidized_copper"
			}
		},
		{
			"weight": 1.0,
			"key": {
				"Type": "block",
				"Name": "securitycraft:blocks/reinforced_oxidized_copper_bulb"
			}
		},
		{
			"weight": 1.0,
			"key": {
				"Type": "block",
				"Name": "securitycraft:blocks/reinforced_oxidized_copper_grate"
			}
		},
		{
			"weight": 1.0,
			"key": {
				"Type": "block",
				"Name": "securitycraft:blocks/reinforced_oxidized_cut_copper"
			}
		},
		{
			"weight": 1.0,
			"key": {
				"Type": "block",
				"Name": "securitycraft:blocks/reinforced_oxidized_cut_copper_slab"
			}
		},
		{
			"weight": 1.0,
			"key": {
				"Type": "block",
				"Name": "securitycraft:blocks/reinforced_oxidized_cut_copper_stairs"
			}
		},
		{
			"weight": 1.0,
			"key": {
				"Type": "block",
				"Name": "securitycraft:blocks/reinforced_packed_ice"
			}
		},
		{
			"weight": 1.0,
			"key": {
				"Type": "block",
				"Name": "securitycraft:blocks/reinforced_packed_mud"
			}
		},
		{
			"weight": 1.0,
			"key": {
				"Type": "block",
				"Name": "securitycraft:blocks/reinforced_pearlescent_froglight"
			}
		},
		{
			"weight": 1.0,
			"key": {
				"Type": "block",
				"Name": "securitycraft:blocks/reinforced_pink_carpet"
			}
		},
		{
			"weight": 1.0,
			"key": {
				"Type": "block",
				"Name": "securitycraft:blocks/reinforced_pink_concrete"
			}
		},
		{
			"weight": 1.0,
			"key": {
				"Type": "block",
				"Name": "securitycraft:blocks/reinforced_pink_glazed_terracotta"
			}
		},
		{
			"weight": 1.0,
			"key": {
				"Type": "block",
				"Name": "securitycraft:blocks/reinforced_pink_stained_glass"
			}
		},
		{
			"weight": 1.0,
			"key": {
				"Type": "block",
				"Name": "securitycraft:blocks/reinforced_pink_stained_glass_pane"
			}
		},
		{
			"weight": 1.0,
			"key": {
				"Type": "block",
				"Name": "securitycraft:blocks/reinforced_pink_terracotta"
			}
		},
		{
			"weight": 1.0,
			"key": {
				"Type": "block",
				"Name": "securitycraft:blocks/reinforced_pink_wool"
			}
		},
		{
			"weight": 1.0,
			"key": {
				"Type": "block",
				"Name": "securitycraft:blocks/reinforced_piston"
			}
		},
		{
			"weight": 1.0,
			"key": {
				"Type": "block",
				"Name": "securitycraft:blocks/reinforced_podzol"
			}
		},
		{
			"weight": 1.0,
			"key": {
				"Type": "block",
				"Name": "securitycraft:blocks/reinforced_polished_andesite"
			}
		},
		{
			"weight": 1.0,
			"key": {
				"Type": "block",
				"Name": "securitycraft:blocks/reinforced_polished_andesite_slab"
			}
		},
		{
			"weight": 1.0,
			"key": {
				"Type": "block",
				"Name": "securitycraft:blocks/reinforced_polished_andesite_stairs"
			}
		},
		{
			"weight": 1.0,
			"key": {
				"Type": "block",
				"Name": "securitycraft:blocks/reinforced_polished_basalt"
			}
		},
		{
			"weight": 1.0,
			"key": {
				"Type": "block",
				"Name": "securitycraft:blocks/reinforced_polished_blackstone"
			}
		},
		{
			"weight": 1.0,
			"key": {
				"Type": "block",
				"Name": "securitycraft:blocks/reinforced_polished_blackstone_brick_slab"
			}
		},
		{
			"weight": 1.0,
			"key": {
				"Type": "block",
				"Name": "securitycraft:blocks/reinforced_polished_blackstone_brick_stairs"
			}
		},
		{
			"weight": 1.0,
			"key": {
				"Type": "block",
				"Name": "securitycraft:blocks/reinforced_polished_blackstone_brick_wall"
			}
		},
		{
			"weight": 1.0,
			"key": {
				"Type": "block",
				"Name": "securitycraft:blocks/reinforced_polished_blackstone_bricks"
			}
		},
		{
			"weight": 1.0,
			"key": {
				"Type": "block",
				"Name": "securitycraft:blocks/reinforced_polished_blackstone_button"
			}
		},
		{
			"weight": 1.0,
			"key": {
				"Type": "block",
				"Name": "securitycraft:blocks/reinforced_polished_blackstone_pressure_plate"
			}
		},
		{
			"weight": 1.0,
			"key": {
				"Type": "block",
				"Name": "securitycraft:blocks/reinforced_polished_blackstone_slab"
			}
		},
		{
			"weight": 1.0,
			"key": {
				"Type": "block",
				"Name": "securitycraft:blocks/reinforced_polished_blackstone_stairs"
			}
		},
		{
			"weight": 1.0,
			"key": {
				"Type": "block",
				"Name": "securitycraft:blocks/reinforced_polished_blackstone_wall"
			}
		},
		{
			"weight": 1.0,
			"key": {
				"Type": "block",
				"Name": "securitycraft:blocks/reinforced_polished_deepslate"
			}
		},
		{
			"weight": 1.0,
			"key": {
				"Type": "block",
				"Name": "securitycraft:blocks/reinforced_polished_deepslate_slab"
			}
		},
		{
			"weight": 1.0,
			"key": {
				"Type": "block",
				"Name": "securitycraft:blocks/reinforced_polished_deepslate_stairs"
			}
		},
		{
			"weight": 1.0,
			"key": {
				"Type": "block",
				"Name": "securitycraft:blocks/reinforced_polished_deepslate_wall"
			}
		},
		{
			"weight": 1.0,
			"key": {
				"Type": "block",
				"Name": "securitycraft:blocks/reinforced_polished_diorite"
			}
		},
		{
			"weight": 1.0,
			"key": {
				"Type": "block",
				"Name": "securitycraft:blocks/reinforced_polished_diorite_slab"
			}
		},
		{
			"weight": 1.0,
			"key": {
				"Type": "block",
				"Name": "securitycraft:blocks/reinforced_polished_diorite_stairs"
			}
		},
		{
			"weight": 1.0,
			"key": {
				"Type": "block",
				"Name": "securitycraft:blocks/reinforced_polished_granite"
			}
		},
		{
			"weight": 1.0,
			"key": {
				"Type": "block",
				"Name": "securitycraft:blocks/reinforced_polished_granite_slab"
			}
		},
		{
			"weight": 1.0,
			"key": {
				"Type": "block",
				"Name": "securitycraft:blocks/reinforced_polished_granite_stairs"
			}
		},
		{
			"weight": 1.0,
			"key": {
				"Type": "block",
				"Name": "securitycraft:blocks/reinforced_polished_tuff"
			}
		},
		{
			"weight": 1.0,
			"key": {
				"Type": "block",
				"Name": "securitycraft:blocks/reinforced_polished_tuff_slab"
			}
		},
		{
			"weight": 1.0,
			"key": {
				"Type": "block",
				"Name": "securitycraft:blocks/reinforced_polished_tuff_stairs"
			}
		},
		{
			"weight": 1.0,
			"key": {
				"Type": "block",
				"Name": "securitycraft:blocks/reinforced_polished_tuff_wall"
			}
		},
		{
			"weight": 1.0,
			"key": {
				"Type": "block",
				"Name": "securitycraft:blocks/reinforced_powder_snow_cauldron"
			}
		},
		{
			"weight": 1.0,
			"key": {
				"Type": "block",
				"Name": "securitycraft:blocks/reinforced_prismarine"
			}
		},
		{
			"weight": 1.0,
			"key": {
				"Type": "block",
				"Name": "securitycraft:blocks/reinforced_prismarine_brick_slab"
			}
		},
		{
			"weight": 1.0,
			"key": {
				"Type": "block",
				"Name": "securitycraft:blocks/reinforced_prismarine_brick_stairs"
			}
		},
		{
			"weight": 1.0,
			"key": {
				"Type": "block",
				"Name": "securitycraft:blocks/reinforced_prismarine_bricks"
			}
		},
		{
			"weight": 1.0,
			"key": {
				"Type": "block",
				"Name": "securitycraft:blocks/reinforced_prismarine_slab"
			}
		},
		{
			"weight": 1.0,
			"key": {
				"Type": "block",
				"Name": "securitycraft:blocks/reinforced_prismarine_stairs"
			}
		},
		{
			"weight": 1.0,
			"key": {
				"Type": "block",
				"Name": "securitycraft:blocks/reinforced_prismarine_wall"
			}
		},
		{
			"weight": 1.0,
			"key": {
				"Type": "block",
				"Name": "securitycraft:blocks/reinforced_purple_carpet"
			}
		},
		{
			"weight": 1.0,
			"key": {
				"Type": "block",
				"Name": "securitycraft:blocks/reinforced_purple_concrete"
			}
		},
		{
			"weight": 1.0,
			"key": {
				"Type": "block",
				"Name": "securitycraft:blocks/reinforced_purple_glazed_terracotta"
			}
		},
		{
			"weight": 1.0,
			"key": {
				"Type": "block",
				"Name": "securitycraft:blocks/reinforced_purple_stained_glass"
			}
		},
		{
			"weight": 1.0,
			"key": {
				"Type": "block",
				"Name": "securitycraft:blocks/reinforced_purple_stained_glass_pane"
			}
		},
		{
			"weight": 1.0,
			"key": {
				"Type": "block",
				"Name": "securitycraft:blocks/reinforced_purple_terracotta"
			}
		},
		{
			"weight": 1.0,
			"key": {
				"Type": "block",
				"Name": "securitycraft:blocks/reinforced_purple_wool"
			}
		},
		{
			"weight": 1.0,
			"key": {
				"Type": "block",
				"Name": "securitycraft:blocks/reinforced_purpur_block"
			}
		},
		{
			"weight": 1.0,
			"key": {
				"Type": "block",
				"Name": "securitycraft:blocks/reinforced_purpur_pillar"
			}
		},
		{
			"weight": 1.0,
			"key": {
				"Type": "block",
				"Name": "securitycraft:blocks/reinforced_purpur_slab"
			}
		},
		{
			"weight": 1.0,
			"key": {
				"Type": "block",
				"Name": "securitycraft:blocks/reinforced_purpur_stairs"
			}
		},
		{
			"weight": 1.0,
			"key": {
				"Type": "block",
				"Name": "securitycraft:blocks/reinforced_quartz_block"
			}
		},
		{
			"weight": 1.0,
			"key": {
				"Type": "block",
				"Name": "securitycraft:blocks/reinforced_quartz_bricks"
			}
		},
		{
			"weight": 1.0,
			"key": {
				"Type": "block",
				"Name": "securitycraft:blocks/reinforced_quartz_pillar"
			}
		},
		{
			"weight": 1.0,
			"key": {
				"Type": "block",
				"Name": "securitycraft:blocks/reinforced_quartz_slab"
			}
		},
		{
			"weight": 1.0,
			"key": {
				"Type": "block",
				"Name": "securitycraft:blocks/reinforced_quartz_stairs"
			}
		},
		{
			"weight": 1.0,
			"key": {
				"Type": "block",
				"Name": "securitycraft:blocks/reinforced_raw_copper_block"
			}
		},
		{
			"weight": 1.0,
			"key": {
				"Type": "block",
				"Name": "securitycraft:blocks/reinforced_raw_gold_block"
			}
		},
		{
			"weight": 1.0,
			"key": {
				"Type": "block",
				"Name": "securitycraft:blocks/reinforced_raw_iron_block"
			}
		},
		{
			"weight": 1.0,
			"key": {
				"Type": "block",
				"Name": "securitycraft:blocks/reinforced_red_carpet"
			}
		},
		{
			"weight": 1.0,
			"key": {
				"Type": "block",
				"Name": "securitycraft:blocks/reinforced_red_concrete"
			}
		},
		{
			"weight": 1.0,
			"key": {
				"Type": "block",
				"Name": "securitycraft:blocks/reinforced_red_glazed_terracotta"
			}
		},
		{
			"weight": 1.0,
			"key": {
				"Type": "block",
				"Name": "securitycraft:blocks/reinforced_red_nether_brick_slab"
			}
		},
		{
			"weight": 1.0,
			"key": {
				"Type": "block",
				"Name": "securitycraft:blocks/reinforced_red_nether_brick_stairs"
			}
		},
		{
			"weight": 1.0,
			"key": {
				"Type": "block",
				"Name": "securitycraft:blocks/reinforced_red_nether_brick_wall"
			}
		},
		{
			"weight": 1.0,
			"key": {
				"Type": "block",
				"Name": "securitycraft:blocks/reinforced_red_nether_bricks"
			}
		},
		{
			"weight": 1.0,
			"key": {
				"Type": "block",
				"Name": "securitycraft:blocks/reinforced_red_sand"
			}
		},
		{
			"weight": 1.0,
			"key": {
				"Type": "block",
				"Name": "securitycraft:blocks/reinforced_red_sandstone"
			}
		},
		{
			"weight": 1.0,
			"key": {
				"Type": "block",
				"Name": "securitycraft:blocks/reinforced_red_sandstone_slab"
			}
		},
		{
			"weight": 1.0,
			"key": {
				"Type": "block",
				"Name": "securitycraft:blocks/reinforced_red_sandstone_stairs"
			}
		},
		{
			"weight": 1.0,
			"key": {
				"Type": "block",
				"Name": "securitycraft:blocks/reinforced_red_sandstone_wall"
			}
		},
		{
			"weight": 1.0,
			"key": {
				"Type": "block",
				"Name": "securitycraft:blocks/reinforced_red_stained_glass"
			}
		},
		{
			"weight": 1.0,
			"key": {
				"Type": "block",
				"Name": "securitycraft:blocks/reinforced_red_stained_glass_pane"
			}
		},
		{
			"weight": 1.0,
			"key": {
				"Type": "block",
				"Name": "securitycraft:blocks/reinforced_red_terracotta"
			}
		},
		{
			"weight": 1.0,
			"key": {
				"Type": "block",
				"Name": "securitycraft:blocks/reinforced_red_wool"
			}
		},
		{
			"weight": 1.0,
			"key": {
				"Type": "block",
				"Name": "securitycraft:blocks/reinforced_redstone_block"
			}
		},
		{
			"weight": 1.0,
			"key": {
				"Type": "block",
				"Name": "securitycraft:blocks/reinforced_redstone_lamp"
			}
		},
		{
			"weight": 1.0,
			"key": {
				"Type": "block",
				"Name": "securitycraft:blocks/reinforced_rooted_dirt"
			}
		},
		{
			"weight": 1.0,
			"key": {
				"Type": "block",
				"Name": "securitycraft:blocks/reinforced_sand"
			}
		},
		{
			"weight": 1.0,
			"key": {
				"Type": "block",
				"Name": "securitycraft:blocks/reinforced_sandstone"
			}
		},
		{
			"weight": 1.0,
			"key": {
				"Type": "block",
				"Name": "securitycraft:blocks/reinforced_sandstone_slab"
			}
		},
		{
			"weight": 1.0,
			"key": {
				"Type": "block",
				"Name": "securitycraft:blocks/reinforced_sandstone_stairs"
			}
		},
		{
			"weight": 1.0,
			"key": {
				"Type": "block",
				"Name": "securitycraft:blocks/reinforced_sandstone_wall"
			}
		},
		{
			"weight": 1.0,
			"key": {
				"Type": "block",
				"Name": "securitycraft:blocks/reinforced_scaffolding"
			}
		},
		{
			"weight": 1.0,
			"key": {
				"Type": "block",
				"Name": "securitycraft:blocks/reinforced_sea_lantern"
			}
		},
		{
			"weight": 1.0,
			"key": {
				"Type": "block",
				"Name": "securitycraft:blocks/reinforced_shroomlight"
			}
		},
		{
			"weight": 1.0,
			"key": {
				"Type": "block",
				"Name": "securitycraft:blocks/reinforced_smooth_basalt"
			}
		},
		{
			"weight": 1.0,
			"key": {
				"Type": "block",
				"Name": "securitycraft:blocks/reinforced_smooth_crystal_quartz"
			}
		},
		{
			"weight": 1.0,
			"key": {
				"Type": "block",
				"Name": "securitycraft:blocks/reinforced_smooth_crystal_quartz_slab"
			}
		},
		{
			"weight": 1.0,
			"key": {
				"Type": "block",
				"Name": "securitycraft:blocks/reinforced_smooth_crystal_quartz_stairs"
			}
		},
		{
			"weight": 1.0,
			"key": {
				"Type": "block",
				"Name": "securitycraft:blocks/reinforced_smooth_quartz"
			}
		},
		{
			"weight": 1.0,
			"key": {
				"Type": "block",
				"Name": "securitycraft:blocks/reinforced_smooth_quartz_slab"
			}
		},
		{
			"weight": 1.0,
			"key": {
				"Type": "block",
				"Name": "securitycraft:blocks/reinforced_smooth_quartz_stairs"
			}
		},
		{
			"weight": 1.0,
			"key": {
				"Type": "block",
				"Name": "securitycraft:blocks/reinforced_smooth_red_sandstone"
			}
		},
		{
			"weight": 1.0,
			"key": {
				"Type": "block",
				"Name": "securitycraft:blocks/reinforced_smooth_red_sandstone_slab"
			}
		},
		{
			"weight": 1.0,
			"key": {
				"Type": "block",
				"Name": "securitycraft:blocks/reinforced_smooth_red_sandstone_stairs"
			}
		},
		{
			"weight": 1.0,
			"key": {
				"Type": "block",
				"Name": "securitycraft:blocks/reinforced_smooth_sandstone"
			}
		},
		{
			"weight": 1.0,
			"key": {
				"Type": "block",
				"Name": "securitycraft:blocks/reinforced_smooth_sandstone_slab"
			}
		},
		{
			"weight": 1.0,
			"key": {
				"Type": "block",
				"Name": "securitycraft:blocks/reinforced_smooth_sandstone_stairs"
			}
		},
		{
			"weight": 1.0,
			"key": {
				"Type": "block",
				"Name": "securitycraft:blocks/reinforced_smooth_stone"
			}
		},
		{
			"weight": 1.0,
			"key": {
				"Type": "block",
				"Name": "securitycraft:blocks/reinforced_snow_block"
			}
		},
		{
			"weight": 1.0,
			"key": {
				"Type": "block",
				"Name": "securitycraft:blocks/reinforced_soul_lantern"
			}
		},
		{
			"weight": 1.0,
			"key": {
				"Type": "block",
				"Name": "securitycraft:blocks/reinforced_soul_sand"
			}
		},
		{
			"weight": 1.0,
			"key": {
				"Type": "block",
				"Name": "securitycraft:blocks/reinforced_soul_soil"
			}
		},
		{
			"weight": 1.0,
			"key": {
				"Type": "block",
				"Name": "securitycraft:blocks/reinforced_spruce_button"
			}
		},
		{
			"weight": 1.0,
			"key": {
				"Type": "block",
				"Name": "securitycraft:blocks/reinforced_spruce_fence"
			}
		},
		{
			"weight": 1.0,
			"key": {
				"Type": "block",
				"Name": "securitycraft:blocks/reinforced_spruce_fence_gate"
			}
		},
		{
			"weight": 1.0,
			"key": {
				"Type": "block",
				"Name": "securitycraft:blocks/reinforced_spruce_log"
			}
		},
		{
			"weight": 1.0,
			"key": {
				"Type": "block",
				"Name": "securitycraft:blocks/reinforced_spruce_planks"
			}
		},
		{
			"weight": 1.0,
			"key": {
				"Type": "block",
				"Name": "securitycraft:blocks/reinforced_spruce_pressure_plate"
			}
		},
		{
			"weight": 1.0,
			"key": {
				"Type": "block",
				"Name": "securitycraft:blocks/reinforced_spruce_slab"
			}
		},
		{
			"weight": 1.0,
			"key": {
				"Type": "block",
				"Name": "securitycraft:blocks/reinforced_spruce_stairs"
			}
		},
		{
			"weight": 1.0,
			"key": {
				"Type": "block",
				"Name": "securitycraft:blocks/reinforced_spruce_wood"
			}
		},
		{
			"weight": 1.0,
			"key": {
				"Type": "block",
				"Name": "securitycraft:blocks/reinforced_sticky_piston"
			}
		},
		{
			"weight": 1.0,
			"key": {
				"Type": "block",
				"Name": "securitycraft:blocks/reinforced_stone"
			}
		},
		{
			"weight": 1.0,
			"key": {
				"Type": "block",
				"Name": "securitycraft:blocks/reinforced_stone_brick_slab"
			}
		},
		{
			"weight": 1.0,
			"key": {
				"Type": "block",
				"Name": "securitycraft:blocks/reinforced_stone_brick_stairs"
			}
		},
		{
			"weight": 1.0,
			"key": {
				"Type": "block",
				"Name": "securitycraft:blocks/reinforced_stone_brick_wall"
			}
		},
		{
			"weight": 1.0,
			"key": {
				"Type": "block",
				"Name": "securitycraft:blocks/reinforced_stone_bricks"
			}
		},
		{
			"weight": 1.0,
			"key": {
				"Type": "block",
				"Name": "securitycraft:blocks/reinforced_stone_button"
			}
		},
		{
			"weight": 1.0,
			"key": {
				"Type": "block",
				"Name": "securitycraft:blocks/reinforced_stone_pressure_plate"
			}
		},
		{
			"weight": 1.0,
			"key": {
				"Type": "block",
				"Name": "securitycraft:blocks/reinforced_stone_slab"
			}
		},
		{
			"weight": 1.0,
			"key": {
				"Type": "block",
				"Name": "securitycraft:blocks/reinforced_stone_stairs"
			}
		},
		{
			"weight": 1.0,
			"key": {
				"Type": "block",
				"Name": "securitycraft:blocks/reinforced_stripped_acacia_log"
			}
		},
		{
			"weight": 1.0,
			"key": {
				"Type": "block",
				"Name": "securitycraft:blocks/reinforced_stripped_acacia_wood"
			}
		},
		{
			"weight": 1.0,
			"key": {
				"Type": "block",
				"Name": "securitycraft:blocks/reinforced_stripped_bamboo_block"
			}
		},
		{
			"weight": 1.0,
			"key": {
				"Type": "block",
				"Name": "securitycraft:blocks/reinforced_stripped_birch_log"
			}
		},
		{
			"weight": 1.0,
			"key": {
				"Type": "block",
				"Name": "securitycraft:blocks/reinforced_stripped_birch_wood"
			}
		},
		{
			"weight": 1.0,
			"key": {
				"Type": "block",
				"Name": "securitycraft:blocks/reinforced_stripped_cherry_log"
			}
		},
		{
			"weight": 1.0,
			"key": {
				"Type": "block",
				"Name": "securitycraft:blocks/reinforced_stripped_cherry_wood"
			}
		},
		{
			"weight": 1.0,
			"key": {
				"Type": "block",
				"Name": "securitycraft:blocks/reinforced_stripped_crimson_hyphae"
			}
		},
		{
			"weight": 1.0,
			"key": {
				"Type": "block",
				"Name": "securitycraft:blocks/reinforced_stripped_crimson_stem"
			}
		},
		{
			"weight": 1.0,
			"key": {
				"Type": "block",
				"Name": "securitycraft:blocks/reinforced_stripped_dark_oak_log"
			}
		},
		{
			"weight": 1.0,
			"key": {
				"Type": "block",
				"Name": "securitycraft:blocks/reinforced_stripped_dark_oak_wood"
			}
		},
		{
			"weight": 1.0,
			"key": {
				"Type": "block",
				"Name": "securitycraft:blocks/reinforced_stripped_jungle_log"
			}
		},
		{
			"weight": 1.0,
			"key": {
				"Type": "block",
				"Name": "securitycraft:blocks/reinforced_stripped_jungle_wood"
			}
		},
		{
			"weight": 1.0,
			"key": {
				"Type": "block",
				"Name": "securitycraft:blocks/reinforced_stripped_mangrove_log"
			}
		},
		{
			"weight": 1.0,
			"key": {
				"Type": "block",
				"Name": "securitycraft:blocks/reinforced_stripped_mangrove_wood"
			}
		},
		{
			"weight": 1.0,
			"key": {
				"Type": "block",
				"Name": "securitycraft:blocks/reinforced_stripped_oak_log"
			}
		},
		{
			"weight": 1.0,
			"key": {
				"Type": "block",
				"Name": "securitycraft:blocks/reinforced_stripped_oak_wood"
			}
		},
		{
			"weight": 1.0,
			"key": {
				"Type": "block",
				"Name": "securitycraft:blocks/reinforced_stripped_spruce_log"
			}
		},
		{
			"weight": 1.0,
			"key": {
				"Type": "block",
				"Name": "securitycraft:blocks/reinforced_stripped_spruce_wood"
			}
		},
		{
			"weight": 1.0,
			"key": {
				"Type": "block",
				"Name": "securitycraft:blocks/reinforced_stripped_warped_hyphae"
			}
		},
		{
			"weight": 1.0,
			"key": {
				"Type": "block",
				"Name": "securitycraft:blocks/reinforced_stripped_warped_stem"
			}
		},
		{
			"weight": 1.0,
			"key": {
				"Type": "block",
				"Name": "securitycraft:blocks/reinforced_tinted_glass"
			}
		},
		{
			"weight": 1.0,
			"key": {
				"Type": "block",
				"Name": "securitycraft:blocks/reinforced_tuff"
			}
		},
		{
			"weight": 1.0,
			"key": {
				"Type": "block",
				"Name": "securitycraft:blocks/reinforced_tuff_brick_slab"
			}
		},
		{
			"weight": 1.0,
			"key": {
				"Type": "block",
				"Name": "securitycraft:blocks/reinforced_tuff_brick_stairs"
			}
		},
		{
			"weight": 1.0,
			"key": {
				"Type": "block",
				"Name": "securitycraft:blocks/reinforced_tuff_brick_wall"
			}
		},
		{
			"weight": 1.0,
			"key": {
				"Type": "block",
				"Name": "securitycraft:blocks/reinforced_tuff_bricks"
			}
		},
		{
			"weight": 1.0,
			"key": {
				"Type": "block",
				"Name": "securitycraft:blocks/reinforced_tuff_slab"
			}
		},
		{
			"weight": 1.0,
			"key": {
				"Type": "block",
				"Name": "securitycraft:blocks/reinforced_tuff_stairs"
			}
		},
		{
			"weight": 1.0,
			"key": {
				"Type": "block",
				"Name": "securitycraft:blocks/reinforced_tuff_wall"
			}
		},
		{
			"weight": 1.0,
			"key": {
				"Type": "block",
				"Name": "securitycraft:blocks/reinforced_verdant_froglight"
			}
		},
		{
			"weight": 1.0,
			"key": {
				"Type": "block",
				"Name": "securitycraft:blocks/reinforced_warped_button"
			}
		},
		{
			"weight": 1.0,
			"key": {
				"Type": "block",
				"Name": "securitycraft:blocks/reinforced_warped_fence"
			}
		},
		{
			"weight": 1.0,
			"key": {
				"Type": "block",
				"Name": "securitycraft:blocks/reinforced_warped_fence_gate"
			}
		},
		{
			"weight": 1.0,
			"key": {
				"Type": "block",
				"Name": "securitycraft:blocks/reinforced_warped_hyphae"
			}
		},
		{
			"weight": 1.0,
			"key": {
				"Type": "block",
				"Name": "securitycraft:blocks/reinforced_warped_nylium"
			}
		},
		{
			"weight": 1.0,
			"key": {
				"Type": "block",
				"Name": "securitycraft:blocks/reinforced_warped_planks"
			}
		},
		{
			"weight": 1.0,
			"key": {
				"Type": "block",
				"Name": "securitycraft:blocks/reinforced_warped_pressure_plate"
			}
		},
		{
			"weight": 1.0,
			"key": {
				"Type": "block",
				"Name": "securitycraft:blocks/reinforced_warped_slab"
			}
		},
		{
			"weight": 1.0,
			"key": {
				"Type": "block",
				"Name": "securitycraft:blocks/reinforced_warped_stairs"
			}
		},
		{
			"weight": 1.0,
			"key": {
				"Type": "block",
				"Name": "securitycraft:blocks/reinforced_warped_stem"
			}
		},
		{
			"weight": 1.0,
			"key": {
				"Type": "block",
				"Name": "securitycraft:blocks/reinforced_warped_wart_block"
			}
		},
		{
			"weight": 1.0,
			"key": {
				"Type": "block",
				"Name": "securitycraft:blocks/reinforced_water_cauldron"
			}
		},
		{
			"weight": 1.0,
			"key": {
				"Type": "block",
				"Name": "securitycraft:blocks/reinforced_weathered_chiseled_copper"
			}
		},
		{
			"weight": 1.0,
			"key": {
				"Type": "block",
				"Name": "securitycraft:blocks/reinforced_weathered_copper"
			}
		},
		{
			"weight": 1.0,
			"key": {
				"Type": "block",
				"Name": "securitycraft:blocks/reinforced_weathered_copper_bulb"
			}
		},
		{
			"weight": 1.0,
			"key": {
				"Type": "block",
				"Name": "securitycraft:blocks/reinforced_weathered_copper_grate"
			}
		},
		{
			"weight": 1.0,
			"key": {
				"Type": "block",
				"Name": "securitycraft:blocks/reinforced_weathered_cut_copper"
			}
		},
		{
			"weight": 1.0,
			"key": {
				"Type": "block",
				"Name": "securitycraft:blocks/reinforced_weathered_cut_copper_slab"
			}
		},
		{
			"weight": 1.0,
			"key": {
				"Type": "block",
				"Name": "securitycraft:blocks/reinforced_weathered_cut_copper_stairs"
			}
		},
		{
			"weight": 1.0,
			"key": {
				"Type": "block",
				"Name": "securitycraft:blocks/reinforced_white_carpet"
			}
		},
		{
			"weight": 1.0,
			"key": {
				"Type": "block",
				"Name": "securitycraft:blocks/reinforced_white_concrete"
			}
		},
		{
			"weight": 1.0,
			"key": {
				"Type": "block",
				"Name": "securitycraft:blocks/reinforced_white_glazed_terracotta"
			}
		},
		{
			"weight": 1.0,
			"key": {
				"Type": "block",
				"Name": "securitycraft:blocks/reinforced_white_stained_glass"
			}
		},
		{
			"weight": 1.0,
			"key": {
				"Type": "block",
				"Name": "securitycraft:blocks/reinforced_white_stained_glass_pane"
			}
		},
		{
			"weight": 1.0,
			"key": {
				"Type": "block",
				"Name": "securitycraft:blocks/reinforced_white_terracotta"
			}
		},
		{
			"weight": 1.0,
			"key": {
				"Type": "block",
				"Name": "securitycraft:blocks/reinforced_white_wool"
			}
		},
		{
			"weight": 1.0,
			"key": {
				"Type": "block",
				"Name": "securitycraft:blocks/reinforced_yellow_carpet"
			}
		},
		{
			"weight": 1.0,
			"key": {
				"Type": "block",
				"Name": "securitycraft:blocks/reinforced_yellow_concrete"
			}
		},
		{
			"weight": 1.0,
			"key": {
				"Type": "block",
				"Name": "securitycraft:blocks/reinforced_yellow_glazed_terracotta"
			}
		},
		{
			"weight": 1.0,
			"key": {
				"Type": "block",
				"Name": "securitycraft:blocks/reinforced_yellow_stained_glass"
			}
		},
		{
			"weight": 1.0,
			"key": {
				"Type": "block",
				"Name": "securitycraft:blocks/reinforced_yellow_stained_glass_pane"
			}
		},
		{
			"weight": 1.0,
			"key": {
				"Type": "block",
				"Name": "securitycraft:blocks/reinforced_yellow_terracotta"
			}
		},
		{
			"weight": 1.0,
			"key": {
				"Type": "block",
				"Name": "securitycraft:blocks/reinforced_yellow_wool"
			}
		},
		{
			"weight": 1.0,
			"key": {
				"Type": "block",
				"Name": "securitycraft:blocks/retinal_scanner"
			}
		},
		{
			"weight": 1.0,
			"key": {
				"Type": "block",
				"Name": "securitycraft:blocks/rift_stabilizer"
			}
		},
		{
			"weight": 1.0,
			"key": {
				"Type": "block",
				"Name": "securitycraft:blocks/sand_mine"
			}
		},
		{
			"weight": 1.0,
			"key": {
				"Type": "block",
				"Name": "securitycraft:blocks/scanner_door"
			}
		},
		{
			"weight": 1.0,
			"key": {
				"Type": "block",
				"Name": "securitycraft:blocks/scanner_trapdoor"
			}
		},
		{
			"weight": 1.0,
			"key": {
				"Type": "block",
				"Name": "securitycraft:blocks/secret_acacia_hanging_sign"
			}
		},
		{
			"weight": 1.0,
			"key": {
				"Type": "block",
				"Name": "securitycraft:blocks/secret_acacia_sign_standing"
			}
		},
		{
			"weight": 1.0,
			"key": {
				"Type": "block",
				"Name": "securitycraft:blocks/secret_acacia_sign_wall"
			}
		},
		{
			"weight": 1.0,
			"key": {
				"Type": "block",
				"Name": "securitycraft:blocks/secret_acacia_wall_hanging_sign"
			}
		},
		{
			"weight": 1.0,
			"key": {
				"Type": "block",
				"Name": "securitycraft:blocks/secret_bamboo_hanging_sign"
			}
		},
		{
			"weight": 1.0,
			"key": {
				"Type": "block",
				"Name": "securitycraft:blocks/secret_bamboo_sign_standing"
			}
		},
		{
			"weight": 1.0,
			"key": {
				"Type": "block",
				"Name": "securitycraft:blocks/secret_bamboo_sign_wall"
			}
		},
		{
			"weight": 1.0,
			"key": {
				"Type": "block",
				"Name": "securitycraft:blocks/secret_bamboo_wall_hanging_sign"
			}
		},
		{
			"weight": 1.0,
			"key": {
				"Type": "block",
				"Name": "securitycraft:blocks/secret_birch_hanging_sign"
			}
		},
		{
			"weight": 1.0,
			"key": {
				"Type": "block",
				"Name": "securitycraft:blocks/secret_birch_sign_standing"
			}
		},
		{
			"weight": 1.0,
			"key": {
				"Type": "block",
				"Name": "securitycraft:blocks/secret_birch_sign_wall"
			}
		},
		{
			"weight": 1.0,
			"key": {
				"Type": "block",
				"Name": "securitycraft:blocks/secret_birch_wall_hanging_sign"
			}
		},
		{
			"weight": 1.0,
			"key": {
				"Type": "block",
				"Name": "securitycraft:blocks/secret_cherry_hanging_sign"
			}
		},
		{
			"weight": 1.0,
			"key": {
				"Type": "block",
				"Name": "securitycraft:blocks/secret_cherry_sign_standing"
			}
		},
		{
			"weight": 1.0,
			"key": {
				"Type": "block",
				"Name": "securitycraft:blocks/secret_cherry_sign_wall"
			}
		},
		{
			"weight": 1.0,
			"key": {
				"Type": "block",
				"Name": "securitycraft:blocks/secret_cherry_wall_hanging_sign"
			}
		},
		{
			"weight": 1.0,
			"key": {
				"Type": "block",
				"Name": "securitycraft:blocks/secret_crimson_hanging_sign"
			}
		},
		{
			"weight": 1.0,
			"key": {
				"Type": "block",
				"Name": "securitycraft:blocks/secret_crimson_sign_standing"
			}
		},
		{
			"weight": 1.0,
			"key": {
				"Type": "block",
				"Name": "securitycraft:blocks/secret_crimson_sign_wall"
			}
		},
		{
			"weight": 1.0,
			"key": {
				"Type": "block",
				"Name": "securitycraft:blocks/secret_crimson_wall_hanging_sign"
			}
		},
		{
			"weight": 1.0,
			"key": {
				"Type": "block",
				"Name": "securitycraft:blocks/secret_dark_oak_hanging_sign"
			}
		},
		{
			"weight": 1.0,
			"key": {
				"Type": "block",
				"Name": "securitycraft:blocks/secret_dark_oak_sign_standing"
			}
		},
		{
			"weight": 1.0,
			"key": {
				"Type": "block",
				"Name": "securitycraft:blocks/secret_dark_oak_sign_wall"
			}
		},
		{
			"weight": 1.0,
			"key": {
				"Type": "block",
				"Name": "securitycraft:blocks/secret_dark_oak_wall_hanging_sign"
			}
		},
		{
			"weight": 1.0,
			"key": {
				"Type": "block",
				"Name": "securitycraft:blocks/secret_jungle_hanging_sign"
			}
		},
		{
			"weight": 1.0,
			"key": {
				"Type": "block",
				"Name": "securitycraft:blocks/secret_jungle_sign_standing"
			}
		},
		{
			"weight": 1.0,
			"key": {
				"Type": "block",
				"Name": "securitycraft:blocks/secret_jungle_sign_wall"
			}
		},
		{
			"weight": 1.0,
			"key": {
				"Type": "block",
				"Name": "securitycraft:blocks/secret_jungle_wall_hanging_sign"
			}
		},
		{
			"weight": 1.0,
			"key": {
				"Type": "block",
				"Name": "securitycraft:blocks/secret_mangrove_hanging_sign"
			}
		},
		{
			"weight": 1.0,
			"key": {
				"Type": "block",
				"Name": "securitycraft:blocks/secret_mangrove_sign_standing"
			}
		},
		{
			"weight": 1.0,
			"key": {
				"Type": "block",
				"Name": "securitycraft:blocks/secret_mangrove_sign_wall"
			}
		},
		{
			"weight": 1.0,
			"key": {
				"Type": "block",
				"Name": "securitycraft:blocks/secret_mangrove_wall_hanging_sign"
			}
		},
		{
			"weight": 1.0,
			"key": {
				"Type": "block",
				"Name": "securitycraft:blocks/secret_oak_hanging_sign"
			}
		},
		{
			"weight": 1.0,
			"key": {
				"Type": "block",
				"Name": "securitycraft:blocks/secret_oak_wall_hanging_sign"
			}
		},
		{
			"weight": 1.0,
			"key": {
				"Type": "block",
				"Name": "securitycraft:blocks/secret_sign_standing"
			}
		},
		{
			"weight": 1.0,
			"key": {
				"Type": "block",
				"Name": "securitycraft:blocks/secret_sign_wall"
			}
		},
		{
			"weight": 1.0,
			"key": {
				"Type": "block",
				"Name": "securitycraft:blocks/secret_spruce_hanging_sign"
			}
		},
		{
			"weight": 1.0,
			"key": {
				"Type": "block",
				"Name": "securitycraft:blocks/secret_spruce_sign_standing"
			}
		},
		{
			"weight": 1.0,
			"key": {
				"Type": "block",
				"Name": "securitycraft:blocks/secret_spruce_sign_wall"
			}
		},
		{
			"weight": 1.0,
			"key": {
				"Type": "block",
				"Name": "securitycraft:blocks/secret_spruce_wall_hanging_sign"
			}
		},
		{
			"weight": 1.0,
			"key": {
				"Type": "block",
				"Name": "securitycraft:blocks/secret_warped_hanging_sign"
			}
		},
		{
			"weight": 1.0,
			"key": {
				"Type": "block",
				"Name": "securitycraft:blocks/secret_warped_sign_standing"
			}
		},
		{
			"weight": 1.0,
			"key": {
				"Type": "block",
				"Name": "securitycraft:blocks/secret_warped_sign_wall"
			}
		},
		{
			"weight": 1.0,
			"key": {
				"Type": "block",
				"Name": "securitycraft:blocks/secret_warped_wall_hanging_sign"
			}
		},
		{
			"weight": 1.0,
			"key": {
				"Type": "block",
				"Name": "securitycraft:blocks/secure_redstone_interface"
			}
		},
		{
			"weight": 1.0,
			"key": {
				"Type": "block",
				"Name": "securitycraft:blocks/security_camera"
			}
		},
		{
			"weight": 1.0,
			"key": {
				"Type": "block",
				"Name": "securitycraft:blocks/smoker_mine"
			}
		},
		{
			"weight": 1.0,
			"key": {
				"Type": "block",
				"Name": "securitycraft:blocks/smooth_crystal_quartz"
			}
		},
		{
			"weight": 1.0,
			"key": {
				"Type": "block",
				"Name": "securitycraft:blocks/smooth_crystal_quartz_slab"
			}
		},
		{
			"weight": 1.0,
			"key": {
				"Type": "block",
				"Name": "securitycraft:blocks/smooth_crystal_quartz_stairs"
			}
		},
		{
			"weight": 1.0,
			"key": {
				"Type": "block",
				"Name": "securitycraft:blocks/sonic_security_system"
			}
		},
		{
			"weight": 1.0,
			"key": {
				"Type": "block",
				"Name": "securitycraft:blocks/stone_mine"
			}
		},
		{
			"weight": 1.0,
			"key": {
				"Type": "block",
				"Name": "securitycraft:blocks/suspicious_gravel_mine"
			}
		},
		{
			"weight": 1.0,
			"key": {
				"Type": "block",
				"Name": "securitycraft:blocks/suspicious_sand_mine"
			}
		},
		{
			"weight": 1.0,
			"key": {
				"Type": "block",
				"Name": "securitycraft:blocks/track_mine"
			}
		},
		{
			"weight": 1.0,
			"key": {
				"Type": "block",
				"Name": "securitycraft:blocks/trophy_system"
			}
		},
		{
			"weight": 1.0,
			"key": {
				"Type": "block",
				"Name": "securitycraft:blocks/username_logger"
			}
		}
	]
}
