{
	"elements": [
		{
			"weight": 1.0,
			"key": {
				"Type": "block",
				"Name": "ironfurnaces:blocks/allthemodium_furnace"
			}
		},
		{
			"weight": 1.0,
			"key": {
				"Type": "block",
				"Name": "ironfurnaces:blocks/copper_furnace"
			}
		},
		{
			"weight": 1.0,
			"key": {
				"Type": "block",
				"Name": "ironfurnaces:blocks/crystal_furnace"
			}
		},
		{
			"weight": 1.0,
			"key": {
				"Type": "block",
				"Name": "ironfurnaces:blocks/diamond_furnace"
			}
		},
		{
			"weight": 1.0,
			"key": {
				"Type": "block",
				"Name": "ironfurnaces:blocks/emerald_furnace"
			}
		},
		{
			"weight": 1.0,
			"key": {
				"Type": "block",
				"Name": "ironfurnaces:blocks/gold_furnace"
			}
		},
		{
			"weight": 1.0,
			"key": {
				"Type": "block",
				"Name": "ironfurnaces:blocks/heater"
			}
		},
		{
			"weight": 1.0,
			"key": {
				"Type": "block",
				"Name": "ironfurnaces:blocks/iron_furnace"
			}
		},
		{
			"weight": 1.0,
			"key": {
				"Type": "block",
				"Name": "ironfurnaces:blocks/million_furnace"
			}
		},
		{
			"weight": 1.0,
			"key": {
				"Type": "block",
				"Name": "ironfurnaces:blocks/netherite_furnace"
			}
		},
		{
			"weight": 1.0,
			"key": {
				"Type": "block",
				"Name": "ironfurnaces:blocks/obsidian_furnace"
			}
		},
		{
			"weight": 1.0,
			"key": {
				"Type": "block",
				"Name": "ironfurnaces:blocks/silver_furnace"
			}
		},
		{
			"weight": 1.0,
			"key": {
				"Type": "block",
				"Name": "ironfurnaces:blocks/unobtainium_furnace"
			}
		},
		{
			"weight": 1.0,
			"key": {
				"Type": "block",
				"Name": "ironfurnaces:blocks/vibranium_furnace"
			}
		}
	]
}
